{
   "entries":
   [
      {
         "id" : "cc_ex_ceremonial",
         "buffs" : 
         [
            "STRESSDMG-30",
			"STRESSRECOVERY20",
			"DEBUFFRESIST20",
			"EX_CRIT",
			"MAXHP-5"
         ],
         "hero_class_requirements":
         [
            "executioner"
         ],
         "set_id" : "cc_executioner",
         "rarity" : "crimson_court",
         "price" : 50000,
         "limit" : 1,
         "origin_dungeon" : "courtyard"
      },
      {
         "id" : "cc_ex_list",
         "buffs" : 
         [
            "EX_LIST_HEALING",
			"EX_LIST_STRESSHEALING",
			"DMGL-10",
			"DMGH-10"
         ],
         "hero_class_requirements":
         [
            "executioner"
         ],
         "set_id" : "cc_executioner",
         "rarity" : "crimson_court",
         "price" : 50000,
         "limit" : 1,
         "origin_dungeon" : "courtyard"
      }
   ]
}
