{
   "entries":
   [
      {
         "id" : "seraph_holy_chainmail",
         "buffs" : 
         [
            "HOLY_CHAINMAIL_PROT_BUFF"
         ],
         "hero_class_requirements":
         [
            "seraph"
         ],
         "rarity" : "common",
         "price" : 7500,
         "limit" : 0,
         "origin_dungeon" : ""
      },
      {
         "id" : "seraph_faithful_pendant",
         "buffs" : 
         [
            "FAITHFUL_PENDANT_VIRTUE_BUFF"
         ],
         "hero_class_requirements":
         [
            "seraph"
         ],
         "rarity" : "common",
         "price" : 7500,
         "limit" : 0,
         "origin_dungeon" : ""
      },
      {
         "id" : "seraph_barbed_crown",
         "buffs" : 
         [
            "BARBED_CROWN_DMGH_BUFF",
            "BARBED_CROWN_DMGL_BUFF",
            "BARBED_CROWN_PROT_DEBUFF"
         ],
         "hero_class_requirements":
         [
            "seraph"
         ],
         "rarity" : "uncommon",
         "price" : 10000,
         "limit" : 0,
         "origin_dungeon" : ""
      },
      {
         "id" : "seraph_torturers_mask",
         "buffs" : 
         [
            "TORTURERS_MASK_STUN_CHANCE_BUFF",
            "TORTURERS_MASK_BLEEDRESIST_DEBUFF",
            "TORTURERS_MASK_VIRTUE_DEBUFF"
         ],
         "hero_class_requirements":
         [
            "seraph"
         ],
         "rarity" : "rare",
         "price" : 15000,
         "limit" : 0,
         "origin_dungeon" : ""
      },
      {
         "id" : "seraph_radiant_censer",
         "buffs" : 
         [
            "RADIANT_CENSER_STRESS_RESIST_BUFF",
            "RADIANT_CENSER_SCOUTING_CHANCE_BUFF",
            "RADIANT_CENSER_PARTY_SURPRISED_BUFF"
         ],
         "hero_class_requirements":
         [
            "seraph"
         ],
         "rarity" : "very_rare",
         "price" : 25000,
         "limit" : 0,
         "origin_dungeon" : ""
      }
   ]
}
