{
   "buffs":
   [
   
  
	  {
         "id" : "DW_darksword_DMGH_90",
         "stat_type" : "combat_stat_multiply",
         "stat_sub_type" : "damage_high",
         "amount" : 0.05,
         "remove_if_not_active" : false,
         "rule_type" : "lightbelow",
         "is_false_rule" : false,
         "rule_data" : {
            "float" : 90,
            "string" : ""
         },
		 "has_description" : false
      },
	{
         "id" : "DW_darksword_DMGH_80",
         "stat_type" : "combat_stat_multiply",
         "stat_sub_type" : "damage_high",
         "amount" : 0.05,
         "remove_if_not_active" : false,
         "rule_type" : "lightbelow",
         "is_false_rule" : false,
         "rule_data" : {
            "float" : 80,
            "string" : ""
         },
		 "has_description" : false
      },
	  {
         "id" : "DW_darksword_DMGH_70",
         "stat_type" : "combat_stat_multiply",
         "stat_sub_type" : "damage_high",
         "amount" : 0.05,
         "remove_if_not_active" : false,
         "rule_type" : "lightbelow",
         "is_false_rule" : false,
         "rule_data" : {
            "float" : 70,
            "string" : ""
         },
		 "has_description" : false
      },
	  {
         "id" : "DW_darksword_DMGH_60",
         "stat_type" : "combat_stat_multiply",
         "stat_sub_type" : "damage_high",
         "amount" : 0.05,
         "remove_if_not_active" : false,
         "rule_type" : "lightbelow",
         "is_false_rule" : false,
         "rule_data" : {
            "float" : 60,
            "string" : ""
         },
		 "has_description" : false
      },
	  {
         "id" : "DW_darksword_DMGH_50",
         "stat_type" : "combat_stat_multiply",
         "stat_sub_type" : "damage_high",
         "amount" : 0.05,
         "remove_if_not_active" : false,
         "rule_type" : "lightbelow",
         "is_false_rule" : false,
         "rule_data" : {
            "float" : 50,
            "string" : ""
         },
		 "has_description" : false
      },
	  {
         "id" : "DW_darksword_DMGH_40",
         "stat_type" : "combat_stat_multiply",
         "stat_sub_type" : "damage_high",
         "amount" : 0.05,
         "remove_if_not_active" : false,
         "rule_type" : "lightbelow",
         "is_false_rule" : false,
         "rule_data" : {
            "float" : 40,
            "string" : ""
         },
		 "has_description" : false
      },
	  {
         "id" : "DW_darksword_DMGH_30",
         "stat_type" : "combat_stat_multiply",
         "stat_sub_type" : "damage_high",
         "amount" : 0.05,
         "remove_if_not_active" : false,
         "rule_type" : "lightbelow",
         "is_false_rule" : false,
         "rule_data" : {
            "float" : 30,
            "string" : ""
         },
		 "has_description" : false
      },
	  {
         "id" : "DW_darksword_DMGH_20",
         "stat_type" : "combat_stat_multiply",
         "stat_sub_type" : "damage_high",
         "amount" : 0.05,
         "remove_if_not_active" : false,
         "rule_type" : "lightbelow",
         "is_false_rule" : false,
         "rule_data" : {
            "float" : 20,
            "string" : ""
         },
		 "has_description" : false
      },
	  {
         "id" : "DW_darksword_DMGH_10",
         "stat_type" : "combat_stat_multiply",
         "stat_sub_type" : "damage_high",
         "amount" : 0.05,
         "remove_if_not_active" : false,
         "rule_type" : "lightbelow",
         "is_false_rule" : false,
         "rule_data" : {
            "float" : 10,
            "string" : ""
         },
		 "has_description" : false
      },
	  {
         "id" : "DW_darksword_DMGH_00",
         "stat_type" : "combat_stat_add",
         "stat_sub_type" : "damage_high",
         "amount" : 0.03,
         "remove_if_not_active" : false,
         "rule_type" : "lightbelow",
         "is_false_rule" : false,
         "rule_data" : {
            "float" : 1,
            "string" : ""
         },
		 "has_description" : false
      },
	  {
         "id" : "DW_darksword_DMGL_90",
         "stat_type" : "combat_stat_multiply",
         "stat_sub_type" : "damage_low",
         "amount" : 0.05,
         "remove_if_not_active" : false,
         "rule_type" : "lightbelow",
         "is_false_rule" : false,
         "rule_data" : {
            "float" : 90,
            "string" : ""
         },
		 "has_description" : false
      },
	{
         "id" : "DW_darksword_DMGL_80",
         "stat_type" : "combat_stat_multiply",
         "stat_sub_type" : "damage_low",
         "amount" : 0.05,
         "remove_if_not_active" : false,
         "rule_type" : "lightbelow",
         "is_false_rule" : false,
         "rule_data" : {
            "float" : 80,
            "string" : ""
         },
		 "has_description" : false
      },
	  {
         "id" : "DW_darksword_DMGL_70",
         "stat_type" : "combat_stat_multiply",
         "stat_sub_type" : "damage_low",
         "amount" : 0.05,
         "remove_if_not_active" : false,
         "rule_type" : "lightbelow",
         "is_false_rule" : false,
         "rule_data" : {
            "float" : 70,
            "string" : ""
         },
		 "has_description" : false
      },
	  {
         "id" : "DW_darksword_DMGL_60",
         "stat_type" : "combat_stat_multiply",
         "stat_sub_type" : "damage_low",
         "amount" : 0.05,
         "remove_if_not_active" : false,
         "rule_type" : "lightbelow",
         "is_false_rule" : false,
         "rule_data" : {
            "float" : 60,
            "string" : ""
         },
		 "has_description" : false
      },
	  {
         "id" : "DW_darksword_DMGL_50",
         "stat_type" : "combat_stat_multiply",
         "stat_sub_type" : "damage_low",
         "amount" : 0.05,
         "remove_if_not_active" : false,
         "rule_type" : "lightbelow",
         "is_false_rule" : false,
         "rule_data" : {
            "float" : 50,
            "string" : ""
         },
		 "has_description" : false
      },
	  {
         "id" : "DW_darksword_DMGL_40",
         "stat_type" : "combat_stat_multiply",
         "stat_sub_type" : "damage_low",
         "amount" : 0.05,
         "remove_if_not_active" : false,
         "rule_type" : "lightbelow",
         "is_false_rule" : false,
         "rule_data" : {
            "float" : 40,
            "string" : ""
         },
		 "has_description" : false
      },
	  {
         "id" : "DW_darksword_DMGL_30",
         "stat_type" : "combat_stat_multiply",
         "stat_sub_type" : "damage_low",
         "amount" : 0.05,
         "remove_if_not_active" : false,
         "rule_type" : "lightbelow",
         "is_false_rule" : false,
         "rule_data" : {
            "float" : 30,
            "string" : ""
         },
		 "has_description" : false
      },
	  {
         "id" : "DW_darksword_DMGL_20",
         "stat_type" : "combat_stat_multiply",
         "stat_sub_type" : "damage_low",
         "amount" : 0.05,
         "remove_if_not_active" : false,
         "rule_type" : "lightbelow",
         "is_false_rule" : false,
         "rule_data" : {
            "float" : 20,
            "string" : ""
         },
		 "has_description" : false
      },
	  {
         "id" : "DW_darksword_DMGL_10",
         "stat_type" : "combat_stat_multiply",
         "stat_sub_type" : "damage_low",
         "amount" : 0.05,
         "remove_if_not_active" : false,
         "rule_type" : "lightbelow",
         "is_false_rule" : false,
         "rule_data" : {
            "float" : 10,
            "string" : ""
         },
		 "has_description" : false
      },
	  {
         "id" : "DW_darksword_DMGL_00",
         "stat_type" : "combat_stat_add",
         "stat_sub_type" : "damage_low",
         "amount" : 0.03,
         "remove_if_not_active" : false,
         "rule_type" : "lightbelow",
         "is_false_rule" : false,
         "rule_data" : {
            "float" : 1,
            "string" : ""
         },
		 "has_description" : false
      },
	   {
         "id" : "TRINKET_DW_Stress_Dark_90",
         "stat_type" : "stress_dmg_received_percent",
         "stat_sub_type" : "",
         "amount" : -0.03,
         "remove_if_not_active" : false,
         "rule_type" : "lightbelow",
         "is_false_rule" : false,
         "rule_data" : {
            "float" : 90,
            "string" : ""
         },
		 "has_description" : false
      },
	{
         "id" : "TRINKET_DW_Stress_Dark_80",
         "stat_type" : "stress_dmg_received_percent",
         "stat_sub_type" : "",
         "amount" : -0.03,
         "remove_if_not_active" : false,
         "rule_type" : "lightbelow",
         "is_false_rule" : false,
         "rule_data" : {
            "float" : 80,
            "string" : ""
         },
		 "has_description" : false
      },
	  {
         "id" : "TRINKET_DW_Stress_Dark_70",
         "stat_type" : "stress_dmg_received_percent",
         "stat_sub_type" : "",
         "amount" : -0.03,
         "remove_if_not_active" : false,
         "rule_type" : "lightbelow",
         "is_false_rule" : false,
         "rule_data" : {
            "float" : 70,
            "string" : ""
         },
		 "has_description" : false
      },
	  {
         "id" : "TRINKET_DW_Stress_Dark_60",
         "stat_type" : "stress_dmg_received_percent",
         "stat_sub_type" : "",
         "amount" : -0.03,
         "remove_if_not_active" : false,
         "rule_type" : "lightbelow",
         "is_false_rule" : false,
         "rule_data" : {
            "float" : 60,
            "string" : ""
         },
		 "has_description" : false
      },
	  {
         "id" : "TRINKET_DW_Stress_Dark_50",
         "stat_type" : "stress_dmg_received_percent",
         "stat_sub_type" : "",
         "amount" : -0.03,
         "remove_if_not_active" : false,
         "rule_type" : "lightbelow",
         "is_false_rule" : false,
         "rule_data" : {
            "float" : 50,
            "string" : ""
         },
		 "has_description" : false
      },
	  {
         "id" : "TRINKET_DW_Stress_Dark_40",
         "stat_type" : "stress_dmg_received_percent",
         "stat_sub_type" : "",
         "amount" : -0.03,
         "remove_if_not_active" : false,
         "rule_type" : "lightbelow",
         "is_false_rule" : false,
         "rule_data" : {
            "float" : 40,
            "string" : ""
         },
		 "has_description" : false
      },
	  {
         "id" : "TRINKET_DW_Stress_Dark_30",
         "stat_type" : "stress_dmg_received_percent",
         "stat_sub_type" : "",
         "amount" : -0.03,
         "remove_if_not_active" : false,
         "rule_type" : "lightbelow",
         "is_false_rule" : false,
         "rule_data" : {
            "float" : 30,
            "string" : ""
         },
		 "has_description" : false
      },
	  {
         "id" : "TRINKET_DW_Stress_Dark_20",
         "stat_type" : "stress_dmg_received_percent",
         "stat_sub_type" : "",
         "amount" : -0.03,
         "remove_if_not_active" : false,
         "rule_type" : "lightbelow",
         "is_false_rule" : false,
         "rule_data" : {
            "float" : 20,
            "string" : ""
         },
		 "has_description" : false
      },
	  {
         "id" : "TRINKET_DW_Stress_Dark_10",
         "stat_type" : "stress_dmg_received_percent",
         "stat_sub_type" : "",
         "amount" : -0.03,
         "remove_if_not_active" : false,
         "rule_type" : "lightbelow",
         "is_false_rule" : false,
         "rule_data" : {
            "float" : 10,
            "string" : ""
         },
		 "has_description" : false
      },
	  {
         "id" : "TRINKET_DW_Stress_Dark_00",
         "stat_type" : "stress_dmg_received_percent",
         "stat_sub_type" : "",
         "amount" : -0.03,
         "remove_if_not_active" : false,
         "rule_type" : "lightbelow",
         "is_false_rule" : false,
         "rule_data" : {
            "float" : 1,
            "string" : ""
         },
		 "has_description" : false
      },
	  
	   {
         "id" : "DW_darksword_DMGL_00",
         "stat_type" : "combat_stat_add",
         "stat_sub_type" : "damage_low",
         "amount" : 0.03,
         "remove_if_not_active" : false,
         "rule_type" : "lightbelow",
         "is_false_rule" : false,
         "rule_data" : {
            "float" : 1,
            "string" : ""
         },
		 "has_description" : false
      },
	   {
         "id" : "TRINKET_DW_ACC_Dark_90",
         "stat_type" : "combat_stat_add",
         "stat_sub_type" : "attack_rating",
         "amount" : 0.01,
         "remove_if_not_active" : false,
         "rule_type" : "lightbelow",
         "is_false_rule" : false,
         "rule_data" : {
            "float" : 90,
            "string" : ""
         },
		 "has_description" : false
      },
	{
         "id" : "TRINKET_DW_ACC_Dark_80",
         "stat_type" : "combat_stat_add",
         "stat_sub_type" : "attack_rating",
         "amount" : 0.01,
         "remove_if_not_active" : false,
         "rule_type" : "lightbelow",
         "is_false_rule" : false,
         "rule_data" : {
            "float" : 80,
            "string" : ""
         },
		 "has_description" : false
      },
	  {
         "id" : "TRINKET_DW_ACC_Dark_70",
         "stat_type" : "combat_stat_add",
         "stat_sub_type" : "attack_rating",
         "amount" : 0.01,
         "remove_if_not_active" : false,
         "rule_type" : "lightbelow",
         "is_false_rule" : false,
         "rule_data" : {
            "float" : 70,
            "string" : ""
         },
		 "has_description" : false
      },
	  {
         "id" : "TRINKET_DW_ACC_Dark_60",
         "stat_type" : "combat_stat_add",
         "stat_sub_type" : "attack_rating",
         "amount" : 0.01,
         "remove_if_not_active" : false,
         "rule_type" : "lightbelow",
         "is_false_rule" : false,
         "rule_data" : {
            "float" : 60,
            "string" : ""
         },
		 "has_description" : false
      },
	  {
         "id" : "TRINKET_DW_ACC_Dark_50",
         "stat_type" : "combat_stat_add",
         "stat_sub_type" : "attack_rating",
         "amount" :0.01,
         "remove_if_not_active" : false,
         "rule_type" : "lightbelow",
         "is_false_rule" : false,
         "rule_data" : {
            "float" : 50,
            "string" : ""
         },
		 "has_description" : false
      },
	  {
         "id" : "TRINKET_DW_ACC_Dark_40",
         "stat_type" : "combat_stat_add",
         "stat_sub_type" : "attack_rating",
         "amount" : 0.01,
         "remove_if_not_active" : false,
         "rule_type" : "lightbelow",
         "is_false_rule" : false,
         "rule_data" : {
            "float" : 40,
            "string" : ""
         },
		 "has_description" : false
      },
	  {
         "id" : "TRINKET_DW_ACC_Dark_30",
         "stat_type" : "combat_stat_add",
         "stat_sub_type" : "attack_rating",
         "amount" : 0.01,
         "remove_if_not_active" : false,
         "rule_type" : "lightbelow",
         "is_false_rule" : false,
         "rule_data" : {
            "float" : 30,
            "string" : ""
         },
		 "has_description" : false
      },
	  {
         "id" : "TRINKET_DW_ACC_Dark_20",
         "stat_type" : "combat_stat_add",
         "stat_sub_type" : "attack_rating",
         "amount" : 0.01,
         "remove_if_not_active" : false,
         "rule_type" : "lightbelow",
         "is_false_rule" : false,
         "rule_data" : {
            "float" : 20,
            "string" : ""
         },
		 "has_description" : false
      },
	  {
         "id" : "TRINKET_DW_ACC_Dark_10",
         "stat_type" : "combat_stat_add",
         "stat_sub_type" : "attack_rating",
         "amount" : 0.01,
         "remove_if_not_active" : false,
         "rule_type" : "lightbelow",
         "is_false_rule" : false,
         "rule_data" : {
            "float" : 10,
            "string" : ""
         },
		 "has_description" : false
      },
	  {
         "id" : "TRINKET_DW_ACC_Dark_00",
         "stat_type" : "combat_stat_add",
         "stat_sub_type" : "attack_rating",
         "amount" : 0.01,
         "remove_if_not_active" : false,
         "rule_type" : "lightbelow",
         "is_false_rule" : false,
         "rule_data" : {
            "float" : 1,
            "string" : ""
         },
		 "has_description" : false
      },
	   {
         "id" : "TRINKET_DW_Pierce_Dark_90",
         "stat_type" : "ignore_protection",
         "stat_sub_type" : "",
         "amount" : 0.03,
         "remove_if_not_active" : false,
         "rule_type" : "lightbelow",
         "is_false_rule" : false,
         "rule_data" : {
            "float" : 90,
            "string" : ""
         },
		 "has_description" : false
      },
	{
         "id" : "TRINKET_DW_Pierce_Dark_80",
         "stat_type" : "ignore_protection",
         "stat_sub_type" : "",
         "amount" : 0.02,
         "remove_if_not_active" : false,
         "rule_type" : "lightbelow",
         "is_false_rule" : false,
         "rule_data" : {
            "float" : 80,
            "string" : ""
         },
		 "has_description" : false
      },
	  {
         "id" : "TRINKET_DW_Pierce_Dark_70",
         "stat_type" : "ignore_protection",
         "stat_sub_type" : "",
         "amount" : 0.02,
         "remove_if_not_active" : false,
         "rule_type" : "lightbelow",
         "is_false_rule" : false,
         "rule_data" : {
            "float" : 70,
            "string" : ""
         },
		 "has_description" : false
      },
	  {
         "id" : "TRINKET_DW_Pierce_Dark_60",
         "stat_type" : "ignore_protection",
         "stat_sub_type" : "",
         "amount" : 0.02,
         "remove_if_not_active" : false,
         "rule_type" : "lightbelow",
         "is_false_rule" : false,
         "rule_data" : {
            "float" : 60,
            "string" : ""
         },
		 "has_description" : false
      },
	  {
         "id" : "TRINKET_DW_Pierce_Dark_50",
         "stat_type" : "ignore_protection",
         "stat_sub_type" : "",
         "amount" : 0.02,
         "remove_if_not_active" : false,
         "rule_type" : "lightbelow",
         "is_false_rule" : false,
         "rule_data" : {
            "float" : 50,
            "string" : ""
         },
		 "has_description" : false
      },
	  {
         "id" : "TRINKET_DW_Pierce_Dark_40",
         "stat_type" : "ignore_protection",
         "stat_sub_type" : "",
         "amount" : 0.02,
         "remove_if_not_active" : false,
         "rule_type" : "lightbelow",
         "is_false_rule" : false,
         "rule_data" : {
            "float" : 40,
            "string" : ""
         },
		 "has_description" : false
      },
	  {
         "id" : "TRINKET_DW_Pierce_Dark_30",
         "stat_type" : "ignore_protection",
         "stat_sub_type" : "",
         "amount" : 0.02,
         "remove_if_not_active" : false,
         "rule_type" : "lightbelow",
         "is_false_rule" : false,
         "rule_data" : {
            "float" : 30,
            "string" : ""
         },
		 "has_description" : false
      },
	  {
         "id" : "TRINKET_DW_Pierce_Dark_20",
         "stat_type" : "ignore_protection",
         "stat_sub_type" : "",
         "amount" : 0.02,
         "remove_if_not_active" : false,
         "rule_type" : "lightbelow",
         "is_false_rule" : false,
         "rule_data" : {
            "float" : 20,
            "string" : ""
         },
		 "has_description" : false
      },
	  {
         "id" : "TRINKET_DW_Pierce_Dark_10",
         "stat_type" : "ignore_protection",
         "stat_sub_type" : "",
         "amount" : 0.02,
         "remove_if_not_active" : false,
         "rule_type" : "lightbelow",
         "is_false_rule" : false,
         "rule_data" : {
            "float" : 10,
            "string" : ""
         },
		 "has_description" : false
      },
	   {
         "id" : "TRINKET_DW_Pierce_Dark_00",
         "stat_type" : "ignore_protection",
         "stat_sub_type" : "",
         "amount" : 0.02,
         "remove_if_not_active" : false,
         "rule_type" : "lightbelow",
         "is_false_rule" : false,
         "rule_data" : {
            "float" : 1,
            "string" : ""
         },
		 "has_description" : false
      },
	   {
         "id" : "DW_TRINKET_Plate_DMGREC_00",
         "stat_type" : "damage_received_percent",
         "stat_sub_type" : "",
         "amount" : -0.02,
         "remove_if_not_active" : false,
         "rule_type" : "lightbelow",
         "is_false_rule" : false,
         "rule_data" : {
            "float" : 1,
            "string" : ""
         },
		 "has_description": false
      },
	  {
         "id" : "DW_TRINKET_Plate_DMGREC_10",
         "stat_type" : "damage_received_percent",
         "stat_sub_type" : "",
         "amount" : -0.02,
         "remove_if_not_active" : false,
         "rule_type" : "lightbelow",
         "is_false_rule" : false,
         "rule_data" : {
            "float" : 10,
            "string" : ""
         },
		 "has_description": false
      },
	  {
         "id" : "DW_TRINKET_Plate_DMGREC_20",
         "stat_type" : "damage_received_percent",
         "stat_sub_type" : "",
         "amount" : -0.02,
         "remove_if_not_active" : false,
         "rule_type" : "lightbelow",
         "is_false_rule" : false,
         "rule_data" : {
            "float" : 20,
            "string" : ""
         },
		 "has_description": false
      },
	  {
         "id" : "DW_TRINKET_Plate_DMGREC_30",
         "stat_type" : "damage_received_percent",
         "stat_sub_type" : "",
         "amount" : -0.02,
         "remove_if_not_active" : false,
         "rule_type" : "lightbelow",
         "is_false_rule" : false,
         "rule_data" : {
            "float" : 30,
            "string" : ""
         },
		 "has_description": false
      },
	   {
         "id" : "DW_TRINKET_Plate_DMGREC_40",
         "stat_type" : "damage_received_percent",
         "stat_sub_type" : "",
         "amount" : -0.02,
         "remove_if_not_active" : false,
         "rule_type" : "lightbelow",
         "is_false_rule" : false,
         "rule_data" : {
            "float" : 40,
            "string" : ""
         },
		 "has_description": false
      },
	   {
         "id" : "DW_TRINKET_Plate_DMGREC_50",
         "stat_type" : "damage_received_percent",
         "stat_sub_type" : "",
         "amount" : -0.02,
         "remove_if_not_active" : false,
         "rule_type" : "lightbelow",
         "is_false_rule" : false,
         "rule_data" : {
            "float" : 50,
            "string" : ""
         },
		 "has_description": false
      },
	   {
         "id" : "DW_TRINKET_Plate_DMGREC_60",
         "stat_type" : "damage_received_percent",
         "stat_sub_type" : "",
         "amount" : -0.02,
         "remove_if_not_active" : false,
         "rule_type" : "lightbelow",
         "is_false_rule" : false,
         "rule_data" : {
            "float" : 60,
            "string" : ""
         },
		 "has_description": false
      },
	   {
         "id" : "DW_TRINKET_Plate_DMGREC_70",
         "stat_type" : "damage_received_percent",
         "stat_sub_type" : "",
         "amount" : -0.02,
         "remove_if_not_active" : false,
         "rule_type" : "lightbelow",
         "is_false_rule" : false,
         "rule_data" : {
            "float" : 70,
            "string" : ""
         },
		 "has_description": false
      },
	   {
         "id" : "DW_TRINKET_Plate_DMGREC_80",
         "stat_type" : "damage_received_percent",
         "stat_sub_type" : "",
         "amount" : -0.02,
         "remove_if_not_active" : false,
         "rule_type" : "lightbelow",
         "is_false_rule" : false,
         "rule_data" : {
            "float" : 80,
            "string" : ""
         },
		 "has_description": false
      },
	   {
         "id" : "DW_TRINKET_Plate_DMGREC_90",
         "stat_type" : "damage_received_percent",
         "stat_sub_type" : "",
         "amount" : -0.02,
         "remove_if_not_active" : false,
         "rule_type" : "lightbelow",
         "is_false_rule" : false,
         "rule_data" : {
            "float" : 90,
            "string" : ""
         },
		 "has_description": false
      }
	  

	
	
	    	  
	  
  
	
	 
   ]
}
