{
	"buffs":
	[
		{
         "id" : "SS_dmg_stress_L1",
         "stat_type" : "combat_stat_multiply",
         "stat_sub_type" : "damage_low",
         "amount" : 0.25,
         "remove_if_not_active" : false,
         "rule_type" : "stress_above",
         "is_false_rule" : false,
         "rule_data" : {
            "float" : 30,
            "string" : ""
         }
      },
	  
		{
         "id" : "SS_dmg_stress_H1",
         "stat_type" : "combat_stat_multiply",
         "stat_sub_type" : "damage_high",
         "amount" : 0.25,
         "remove_if_not_active" : false,
         "rule_type" : "stress_above",
         "is_false_rule" : false,
         "rule_data" : {
            "float" : 30,
            "string" : ""
         }
      },
		{
         "id" : "SS_dmg_stress_L2",
         "stat_type" : "combat_stat_multiply",
         "stat_sub_type" : "damage_low",
         "amount" : 0.25,
         "remove_if_not_active" : false,
         "rule_type" : "stress_above",
         "is_false_rule" : false,
         "rule_data" : {
            "float" : 70,
            "string" : ""
         }
      },
	  
		{
         "id" : "SS_dmg_stress_H2",
         "stat_type" : "combat_stat_multiply",
         "stat_sub_type" : "damage_high",
         "amount" : 0.25,
         "remove_if_not_active" : false,
         "rule_type" : "stress_above",
         "is_false_rule" : false,
         "rule_data" : {
            "float" : 70,
            "string" : ""
         }
      },
	  
		{
         "id" : "SS_dmg_stress2_L1",
         "stat_type" : "combat_stat_multiply",
         "stat_sub_type" : "damage_low",
         "amount" : 0.25,
         "remove_if_not_active" : false,
         "rule_type" : "stress_above",
         "is_false_rule" : false,
         "rule_data" : {
            "float" : 130,
            "string" : ""
         }
      },
	  
		{
         "id" : "SS_dmg_stress2_H1",
         "stat_type" : "combat_stat_multiply",
         "stat_sub_type" : "damage_high",
         "amount" : 0.25,
         "remove_if_not_active" : false,
         "rule_type" : "stress_above",
         "is_false_rule" : false,
         "rule_data" : {
            "float" : 130,
            "string" : ""
         }
      },
		{
         "id" : "SS_dmg_stress2_L2",
         "stat_type" : "combat_stat_multiply",
         "stat_sub_type" : "damage_low",
         "amount" : 0.25,
         "remove_if_not_active" : false,
         "rule_type" : "stress_above",
         "is_false_rule" : false,
         "rule_data" : {
            "float" : 170,
            "string" : ""
         }
      },
	  
		{
         "id" : "SS_dmg_stress2_H2",
         "stat_type" : "combat_stat_multiply",
         "stat_sub_type" : "damage_high",
         "amount" : 0.25,
         "remove_if_not_active" : false,
         "rule_type" : "stress_above",
         "is_false_rule" : false,
         "rule_data" : {
            "float" : 170,
            "string" : ""
         }
      },
	  

		{
         "id" : "SS_dmg_stress_40L",
         "stat_type" : "combat_stat_multiply",
         "stat_sub_type" : "damage_low",
         "amount" : 0.20,
         "remove_if_not_active" : false,
         "rule_type" : "stress_above",
         "is_false_rule" : false,
         "rule_data" : {
            "float" : 40,
            "string" : ""
         }
      },
	  
		{
         "id" : "SS_dmg_stress_40H",
         "stat_type" : "combat_stat_multiply",
         "stat_sub_type" : "damage_high",
         "amount" : 0.20,
         "remove_if_not_active" : false,
         "rule_type" : "stress_above",
         "is_false_rule" : false,
         "rule_data" : {
            "float" : 40,
            "string" : ""
         }
      },	
	  
	  	{
         "id" : "SS_dmg_stress_80L",
         "stat_type" : "combat_stat_multiply",
         "stat_sub_type" : "damage_low",
         "amount" : 0.20,
         "remove_if_not_active" : false,
         "rule_type" : "stress_above",
         "is_false_rule" : false,
         "rule_data" : {
            "float" : 80,
            "string" : ""
         }
      },	
	  
	  	{
         "id" : "SS_dmg_stress_80H",
         "stat_type" : "combat_stat_multiply",
         "stat_sub_type" : "damage_high",
         "amount" : 0.20,
         "remove_if_not_active" : false,
         "rule_type" : "stress_above",
         "is_false_rule" : false,
         "rule_data" : {
            "float" : 80,
            "string" : ""
         }
      },
	  
		{
         "id" : "SS_dmg_stress2_40L",
         "stat_type" : "combat_stat_multiply",
         "stat_sub_type" : "damage_low",
         "amount" : 0.20,
         "remove_if_not_active" : false,
         "rule_type" : "stress_above",
         "is_false_rule" : false,
         "rule_data" : {
            "float" : 140,
            "string" : ""
         }
      },
	  
		{
         "id" : "SS_dmg_stress2_40H",
         "stat_type" : "combat_stat_multiply",
         "stat_sub_type" : "damage_high",
         "amount" : 0.20,
         "remove_if_not_active" : false,
         "rule_type" : "stress_above",
         "is_false_rule" : false,
         "rule_data" : {
            "float" : 140,
            "string" : ""
         }
      },	
	  
	  	{
         "id" : "SS_dmg_stress2_80L",
         "stat_type" : "combat_stat_multiply",
         "stat_sub_type" : "damage_low",
         "amount" : 0.20,
         "remove_if_not_active" : false,
         "rule_type" : "stress_above",
         "is_false_rule" : false,
         "rule_data" : {
            "float" : 180,
            "string" : ""
         }
      },	
	  
	  	{
         "id" : "SS_dmg_stress2_80H",
         "stat_type" : "combat_stat_multiply",
         "stat_sub_type" : "damage_high",
         "amount" : 0.20,
         "remove_if_not_active" : false,
         "rule_type" : "stress_above",
         "is_false_rule" : false,
         "rule_data" : {
            "float" : 180,
            "string" : ""
         }
      },
	  
	  	{
         "id" : "stress_tipA",
         "stat_type" : "upgrade_discount",
         "stat_sub_type" : "sooth_tooltipA",
         "amount" : 1,
         "remove_if_not_active" : false,
         "rule_type" : "always",
         "is_false_rule" : false,
         "rule_data" : {
            "float" : 0,
            "string" : ""
         }
      },
	  
	  	{
         "id" : "stress_tipA2",
         "stat_type" : "upgrade_discount",
         "stat_sub_type" : "sooth_tooltipA2",
         "amount" : 1,
         "remove_if_not_active" : false,
         "rule_type" : "always",
         "is_false_rule" : false,
         "rule_data" : {
            "float" : 0,
            "string" : ""
         }
      },
	  
	  	{
         "id" : "stress_tipA3",
         "stat_type" : "upgrade_discount",
         "stat_sub_type" : "sooth_tooltipA3",
         "amount" : 1,
         "remove_if_not_active" : false,
         "rule_type" : "always",
         "is_false_rule" : false,
         "rule_data" : {
            "float" : 0,
            "string" : ""
         }
      },
	  
	  	{
         "id" : "stress_tipA4",
         "stat_type" : "upgrade_discount",
         "stat_sub_type" : "sooth_tooltipA4",
         "amount" : 1,
         "remove_if_not_active" : false,
         "rule_type" : "always",
         "is_false_rule" : false,
         "rule_data" : {
            "float" : 0,
            "string" : ""
         }
      },
	  
	  	{
         "id" : "stress_tipA5",
         "stat_type" : "upgrade_discount",
         "stat_sub_type" : "sooth_tooltipA5",
         "amount" : 1,
         "remove_if_not_active" : false,
         "rule_type" : "always",
         "is_false_rule" : false,
         "rule_data" : {
            "float" : 0,
            "string" : ""
         }
      },
	  
	  	{
         "id" : "stress_tipB",
         "stat_type" : "upgrade_discount",
         "stat_sub_type" : "sooth_tooltipB",
         "amount" : 1,
         "remove_if_not_active" : false,
         "rule_type" : "always",
         "is_false_rule" : false,
         "rule_data" : {
            "float" : 0,
            "string" : ""
         }
      },
	  
	  	{
         "id" : "stress_tipB2",
         "stat_type" : "upgrade_discount",
         "stat_sub_type" : "sooth_tooltipB2",
         "amount" : 1,
         "remove_if_not_active" : false,
         "rule_type" : "always",
         "is_false_rule" : false,
         "rule_data" : {
            "float" : 0,
            "string" : ""
         }
      },
	  
	  	{
         "id" : "stress_tipB3",
         "stat_type" : "upgrade_discount",
         "stat_sub_type" : "sooth_tooltipB3",
         "amount" : 1,
         "remove_if_not_active" : false,
         "rule_type" : "always",
         "is_false_rule" : false,
         "rule_data" : {
            "float" : 0,
            "string" : ""
         }
      },
	  
	  	{
         "id" : "stress_tipB4",
         "stat_type" : "upgrade_discount",
         "stat_sub_type" : "sooth_tooltipB4",
         "amount" : 1,
         "remove_if_not_active" : false,
         "rule_type" : "always",
         "is_false_rule" : false,
         "rule_data" : {
            "float" : 0,
            "string" : ""
         }
      },
	  
	  	{
         "id" : "stress_tipB5",
         "stat_type" : "upgrade_discount",
         "stat_sub_type" : "sooth_tooltipB5",
         "amount" : 1,
         "remove_if_not_active" : false,
         "rule_type" : "always",
         "is_false_rule" : false,
         "rule_data" : {
            "float" : 0,
            "string" : ""
         }
      },
	  
	    {
         "id" : "SOOTH_StressResistance",
         "stat_type" : "stress_dmg_received_percent",
         "stat_sub_type" : "",
         "amount" : -0.8,
         "remove_if_not_active" : false,
         "rule_type" : "always",
         "is_false_rule" : false,
         "rule_data" : {
            "float" : 0,
            "string" : ""
         }
      },

		{
         "id" : "SOOTH_No_tressheal",
         "stat_type" : "stress_heal_received_percent",
         "stat_sub_type" : "",
         "amount" : -0.8,
         "remove_if_not_active" : false,
         "rule_type" : "always",
         "is_false_rule" : false,
         "rule_data" : {
            "float" : 0,
            "string" : ""
         }
      },

        {
         "id" : "SOOTH_stun_resist",
         "stat_type" : "resistance",
         "stat_sub_type" : "stun",
         "amount" : -0.2,
         "remove_if_not_active" : false,
         "rule_type" : "always",
         "is_false_rule" : false,
         "rule_data" : {
            "float" : 0,
            "string" : ""
         }
      },

        {
         "id" : "SOOTH_More_stress",
         "stat_type" : "stress_dmg_received_percent",
         "stat_sub_type" : "",
         "amount" : 0.5,
         "remove_if_not_active" : false,
         "rule_type" : "always",
         "is_false_rule" : false,
         "rule_data" : {
            "float" : 0,
            "string" : ""
         }
      },
	  
      {
         "id" : "SOOTH_miracle_eye_CritReceived_1",
         "stat_type" : "crit_received_chance",
         "stat_sub_type" : "",
         "amount" : 0.05,
         "remove_if_not_active" : false,
         "rule_type" : "always",
         "is_false_rule" : false,
         "rule_data" : {
            "float" : 0,
            "string" : ""
         }
      },
      {
         "id" : "SOOTH_miracle_eye_CritReceived_2",
         "stat_type" : "crit_received_chance",
         "stat_sub_type" : "",
         "amount" : 0.06,
         "remove_if_not_active" : false,
         "rule_type" : "always",
         "is_false_rule" : false,
         "rule_data" : {
            "float" : 0,
            "string" : ""
         }
      },
      {
         "id" : "SOOTH_miracle_eye_CritReceived_3",
         "stat_type" : "crit_received_chance",
         "stat_sub_type" : "",
         "amount" : 0.07,
         "remove_if_not_active" : false,
         "rule_type" : "always",
         "is_false_rule" : false,
         "rule_data" : {
            "float" : 0,
            "string" : ""
         }
      },
      {
         "id" : "SOOTH_miracle_eye_CritReceived_4",
         "stat_type" : "crit_received_chance",
         "stat_sub_type" : "",
         "amount" : 0.08,
         "remove_if_not_active" : false,
         "rule_type" : "always",
         "is_false_rule" : false,
         "rule_data" : {
            "float" : 0,
            "string" : ""
         }
      },
      {
         "id" : "SOOTH_miracle_eye_CritReceived_5",
         "stat_type" : "crit_received_chance",
         "stat_sub_type" : "",
         "amount" : 0.09,
         "remove_if_not_active" : false,
         "rule_type" : "always",
         "is_false_rule" : false,
         "rule_data" : {
            "float" : 0,
            "string" : ""
         }
      },
      {
         "id" : "SOOTH_random_chance",
         "stat_type" : "random_target_attack_chance",
         "stat_sub_type" : "",
         "amount" : 0.2,
         "remove_if_not_active" : false,
         "rule_type" : "always",
         "is_false_rule" : false,
         "rule_data" : {
            "float" : 0,
            "string" : ""
         }
      },
	  
        {
         "id" : "Sooth_t_dodge",
         "stat_type" : "combat_stat_add",
         "stat_sub_type" : "defense_rating",
         "amount" : 0.03,
         "remove_if_not_active" : false,
         "rule_type" : "always",
         "is_false_rule" : false,
         "rule_data" : {
            "float" : 0,
            "string" : ""
         }
      },
	  
        {
         "id" : "Sooth_t_spd",
         "stat_type" : "combat_stat_add",
         "stat_sub_type" : "speed_rating",
         "amount" : -1,
         "remove_if_not_active" : false,
         "rule_type" : "always",
         "is_false_rule" : false,
         "rule_data" : {
            "float" : 0,
            "string" : ""
         }
      },
	  
        {
         "id" : "Sooth_t_less_stress",
         "stat_type" : "stress_dmg_received_percent",
         "stat_sub_type" : "",
         "amount" : -0.15,
         "remove_if_not_active" : false,
         "rule_type" : "always",
         "is_false_rule" : false,
         "rule_data" : {
            "float" : 0,
            "string" : ""
         }
      },
	  
        {
         "id" : "Sooth_t_stressheal",
         "stat_type" : "stress_heal_received_percent",
         "stat_sub_type" : "",
         "amount" : 0.2,
         "remove_if_not_active" : false,
         "rule_type" : "always",
         "is_false_rule" : false,
         "rule_data" : {
            "float" : 0,
            "string" : ""
         }
      },
	  
        {
         "id" : "Sooth_t_debuffchance",
         "stat_type" : "debuff_chance",
         "stat_sub_type" : "",
         "amount" : 0.4,
         "remove_if_not_active" : false,
         "rule_type" : "always",
         "is_false_rule" : false,
         "rule_data" : {
            "float" : 0,
            "string" : ""
         }
      },
	  
        {
         "id" : "Sooth_t_bleedresist",
         "stat_type" : "resistance",
         "stat_sub_type" : "bleed",
         "amount" : -0.25,
         "remove_if_not_active" : false,
         "rule_type" : "always",
         "is_false_rule" : false,
         "rule_data" : {
            "float" : 0,
            "string" : ""
         }
      },
	  
        {
         "id" : "Sooth_t_lessacc",
         "stat_type" : "combat_stat_add",
         "stat_sub_type" : "attack_rating",
         "amount" : -0.03,
         "remove_if_not_active" : false,
         "rule_type" : "always",
         "is_false_rule" : false,
         "rule_data" : {
            "float" : 0,
            "string" : ""
         }
      },
	  
        {
         "id" : "Sooth_t_crit",
         "stat_type" : "combat_stat_add",
         "stat_sub_type" : "crit_chance",
         "amount" : 0.05,
         "remove_if_not_active" : false,
         "rule_type" : "always",
         "is_false_rule" : false,
         "rule_data" : {
            "float" : 0,
            "string" : ""
         }
      },
	 
        {
         "id" : "Sooth_t_moreheal_stress",
         "stat_type" : "stress_heal_percent",
         "stat_sub_type" : "",
         "amount" : 0.33,
         "remove_if_not_active" : false,
         "rule_type" : "always",
         "is_false_rule" : false,
         "rule_data" : {
            "float" : 0,
            "string" : ""
         }
      },
	  
        {
         "id" : "Sooth_t_lessspd",
         "stat_type" : "combat_stat_add",
         "stat_sub_type" : "speed_rating",
         "amount" : -5,
         "remove_if_not_active" : false,
         "rule_type" : "always",
         "is_false_rule" : false,
         "rule_data" : {
            "float" : 0,
            "string" : ""
         }
      },
	  
        {
         "id" : "Sooth_t_moreacc",
         "stat_type" : "combat_stat_add",
         "stat_sub_type" : "attack_rating",
         "amount" : 0.08,
         "remove_if_not_active" : false,
         "rule_type" : "always",
         "is_false_rule" : false,
         "rule_data" : {
            "float" : 0,
            "string" : ""
         }
      },
	  
        {
         "id" : "Sooth_t_lessstressrec",
         "stat_type" : "stress_dmg_received_percent",
         "stat_sub_type" : "",
         "amount" : -0.5,
         "remove_if_not_active" : false,
         "rule_type" : "always",
         "is_false_rule" : false,
         "rule_data" : {
            "float" : 0,
            "string" : ""
         }
      },
	  
        {
         "id" : "Sooth_t_morestunchance",
         "stat_type" : "stun_chance",
         "stat_sub_type" : "",
         "amount" : 0.3,
         "remove_if_not_active" : false,
         "rule_type" : "always",
         "is_false_rule" : false,
         "rule_data" : {
            "float" : 0,
            "string" : ""
         }
      },
	  
        {
         "id" : "Sooth_t_stressDMG_L",
         "stat_type" : "combat_stat_multiply",
         "stat_sub_type" : "damage_low",
         "amount" : 0.25,
         "remove_if_not_active" : false,
         "rule_type" : "stress_below",
         "is_false_rule" : false,
         "rule_data" : {
            "float" : 60,
            "string" : ""
         }
      },
	  
        {
         "id" : "Sooth_t_stressDMG_H",
         "stat_type" : "combat_stat_multiply",
         "stat_sub_type" : "damage_high",
         "amount" : 0.25,
         "remove_if_not_active" : false,
         "rule_type" : "stress_below",
         "is_false_rule" : false,
         "rule_data" : {
            "float" : 60,
            "string" : ""
         }
      },
	  
        {
         "id" : "Sooth_t_stressdodge",
         "stat_type" : "combat_stat_add",
         "stat_sub_type" : "defense_rating",
         "amount" : 0.07,
         "remove_if_not_active" : false,
         "rule_type" : "stress_above",
         "is_false_rule" : false,
         "rule_data" : {
            "float" : 40,
            "string" : ""
         }
      },
	  
        {
         "id" : "Sooth_t_deathblowresist",
         "stat_type" : "resistance",
         "stat_sub_type" : "death_blow",
         "amount" : 0.15,
         "remove_if_not_active" : false,
         "rule_type" : "stress_above",
         "is_false_rule" : false,
         "rule_data" : {
            "float" : 90,
            "string" : ""
         }
      },
	  
        {
         "id" : "Sooth_t_lessmaxhp",
         "stat_type" : "combat_stat_multiply",
         "stat_sub_type" : "max_hp",
         "amount" : -0.15,
         "remove_if_not_active" : false,
         "rule_type" : "always",
         "is_false_rule" : false,
         "rule_data" : {
            "float" : 0,
            "string" : ""
         }
      },
	  
        {
         "id" : "Sooth_t_cc_scouting",
         "stat_type" : "scouting_chance",
         "stat_sub_type" : "",
         "amount" : 0.2,
         "remove_if_not_active" : false,
         "rule_type" : "always",
         "is_false_rule" : false,
         "rule_data" : {
            "float" : 0,
            "string" : ""
         }
      },
	  
        {
         "id" : "Sooth_t_cc_morestress1",
         "stat_type" : "stress_dmg_received_percent",
         "stat_sub_type" : "",
         "amount" : 0.25,
         "remove_if_not_active" : false,
         "rule_type" : "always",
         "is_false_rule" : false,
         "rule_data" : {
            "float" : 0,
            "string" : ""
         }
      },
	  
        {
         "id" : "Sooth_t_cc_maxhp",
         "stat_type" : "combat_stat_multiply",
         "stat_sub_type" : "max_hp",
         "amount" : 0.1,
         "remove_if_not_active" : false,
         "rule_type" : "always",
         "is_false_rule" : false,
         "rule_data" : {
            "float" : 0,
            "string" : ""
         }
      },
	  
        {
         "id" : "Sooth_t_cc_spd",
         "stat_type" : "combat_stat_add",
         "stat_sub_type" : "speed_rating",
         "amount" : 3,
         "remove_if_not_active" : false,
         "rule_type" : "always",
         "is_false_rule" : false,
         "rule_data" : {
            "float" : 0,
            "string" : ""
         }
      },
	  
        {
         "id" : "Sooth_t_cc_morestress2",
         "stat_type" : "stress_dmg_received_percent",
         "stat_sub_type" : "",
         "amount" : 0.25,
         "remove_if_not_active" : false,
         "rule_type" : "always",
         "is_false_rule" : false,
         "rule_data" : {
            "float" : 0,
            "string" : ""
         }
      },
	  
        {
         "id" : "Sooth_t_cc_stressheal",
         "stat_type" : "stress_heal_received_percent",
         "stat_sub_type" : "",
         "amount" : -0.5,
         "remove_if_not_active" : false,
         "rule_type" : "always",
         "is_false_rule" : false,
         "rule_data" : {
            "float" : 0,
            "string" : ""
         }
      },
	  
        {
         "id" : "Sooth_t_cc_accstress",
         "stat_type" : "combat_stat_add",
         "stat_sub_type" : "attack_rating",
         "amount" : 0.07,
         "remove_if_not_active" : false,
         "rule_type" : "stress_above",
         "is_false_rule" : false,
         "rule_data" : {
            "float" : 70,
            "string" : ""
         }
      },
	  
        {
         "id" : "Sooth_af_lessac",
         "stat_type" : "combat_stat_add",
         "stat_sub_type" : "attack_rating",
         "amount" : -0.05,
         "remove_if_not_active" : false,
         "rule_type" : "always",
         "is_false_rule" : false,
         "rule_data" : {
            "float" : 0,
            "string" : ""
         }
      },
	  
        {
         "id" : "Sooth_af_dodge",
         "stat_type" : "combat_stat_add",
         "stat_sub_type" : "defense_rating",
         "amount" : 0.05,
         "remove_if_not_active" : false,
         "rule_type" : "always",
         "is_false_rule" : false,
         "rule_data" : {
            "float" : 0,
            "string" : ""
         }
      },
	  
        {
         "id" : "Sooth_af_spd",
         "stat_type" : "combat_stat_add",
         "stat_sub_type" : "speed_rating",
         "amount" : 3,
         "remove_if_not_active" : false,
         "rule_type" : "always",
         "is_false_rule" : false,
         "rule_data" : {
            "float" : 0,
            "string" : ""
         }
      },
	  
        {
         "id" : "Sooth_t_com_stressheal",
         "stat_type" : "stress_heal_percent",
         "stat_sub_type" : "",
         "amount" :0.5,
         "remove_if_not_active" : false,
         "rule_type" : "stress_below",
         "is_false_rule" : false,
         "rule_data" : {
            "float" : 50,
            "string" : ""
         }
      },
	  
        {
         "id" : "Sooth_t_com_dodge",
         "stat_type" : "combat_stat_add",
         "stat_sub_type" : "defense_rating",
         "amount" : -0.05,
         "remove_if_not_active" : false,
         "rule_type" : "always",
         "is_false_rule" : false,
         "rule_data" : {
            "float" : 0,
            "string" : ""
         }
      },
	  
        {
         "id" : "Sooth_t_com_crit",
         "stat_type" : "combat_stat_add",
         "stat_sub_type" : "crit_chance",
         "amount" : 0.07,
         "remove_if_not_active" : false,
         "rule_type" : "has_item_id",
         "is_false_rule" : false,
         "rule_data" : {
            "float" : 0,
            "string" : "laudanum"
         }
      }
	]
}