<?xml version="1.0" encoding="UTF-8"?>
<root>
    <language id="polish">
        <entry id="hero_class_name_shield_maiden"><![CDATA[Tarczowniczka]]></entry>
        <entry id="action_verbose_body_blacksmith_shield_maiden"><![CDATA[Siła tarczowniczek nie bierze się ze stalowych płyt czy tarczy, ale z siły przysięgi. Uzbrojona w ciężki pancerz, solidną tarczę oraz krótki miecz będzie broniła twoich pierwszych szeregów. 
         
        Chociaż może nie wydawać się na fizycznie silną, jej koncentracja na defensywie oraz proste zdolności medyczne mogą ocalić całą drużynę przed karzącą ręką kostuchy.]]></entry>
 
        <entry id="action_verbose_body_guild_shield_maiden"><![CDATA[Szybciej złamiesz stalową bramę aniżeli przysięgę tarczowniczki. Obietnica udzielenie mocy i wsparcia swym braciom i siostrom w czasie walki i w czasie pogardy. Jest mieczem, rozcinającym mrok. Jest tarczą broniącą ludzkość.
         
        Tarczowniczki są szkolone by bronić i chronić wysokich dostojników w państwach dalekiej północy. Nie ma może dobrych umiejętności ofensywnych, ale dzięki sztuce obrony oraz supportu może długo utrzymywać się na polu bitwy, zyskując czas dla bardziej ofensywnych tyłów.]]></entry>
 
 
        <entry id="action_verbose_body_camping_trainer_shield_maiden"><![CDATA[Podczas pobytu w obozie Tarczowniczka może skorzystać z umiejętności redukcji stresu i bólu swych kompanów. Może też przygotować siebie lub innych do kolejnych potyczek poprzez trening obronny.]]></entry>
 
        <entry id="combat_skill_name_shield_maiden_cross_blade"><![CDATA[Krzyżowe cięcie]]></entry>
        <entry id="combat_skill_name_shield_maiden_front_guard"><![CDATA[Strzeż frontu]]></entry>
            <entry id="combat_skill_name_shield_maiden_ram_shield"><![CDATA[Uderzenie tarczą]]></entry>
            <entry id="combat_skill_name_shield_maiden_avenger"><![CDATA[Mścicielka]]></entry>
            <entry id="combat_skill_name_shield_maiden_guardian"><![CDATA[Gwardzistka]]></entry>
            <entry id="combat_skill_name_shield_maiden_mending_touch"><![CDATA[Nakładanie rąk]]></entry>
            <entry id="combat_skill_name_shield_maiden_indomitable"><![CDATA[Nieustraszenie]]></entry>
            <entry id="combat_skill_name_shield_maiden_move"><![CDATA[Ruch]]></entry>
            <entry id="upgrade_tree_name_shield_maiden.cross_blade"><![CDATA[Krzyżowe cięcie]]></entry>
            <entry id="upgrade_tree_name_shield_maiden.front_guard"><![CDATA[Strzeż frontu]]></entry>
            <entry id="upgrade_tree_name_shield_maiden.ram_shield"><![CDATA[Uderzenie tarczą]]></entry>
            <entry id="upgrade_tree_name_shield_maiden.avenger"><![CDATA[Mścicielka]]></entry>
            <entry id="upgrade_tree_name_shield_maiden.guardian"><![CDATA[Gwardzistka]]></entry>
            <entry id="upgrade_tree_name_shield_maiden.mending_touch"><![CDATA[Nakładanie rąk]]></entry>
            <entry id="upgrade_tree_name_shield_maiden.indomitable"><![CDATA[Nieustraszenie]]></entry>
 
            <entry id="shield_maiden_weapon_0"><![CDATA[Zardzewiały miecz]]></entry>
            <entry id="shield_maiden_weapon_1"><![CDATA[Zwyczajny miecz]]></entry>
            <entry id="shield_maiden_weapon_2"><![CDATA[Ostry miecz]]></entry>
            <entry id="shield_maiden_weapon_3"><![CDATA[Porządny miecz]]></entry>
            <entry id="shield_maiden_weapon_4"><![CDATA["Dar konunga"]]></entry>
            <entry id="upgrade_tree_name_shield_maiden.weapon"><![CDATA[Krótki miecz]]></entry>
            <entry id="shield_maiden_armour_0"><![CDATA[Sklepione płyty]]></entry>
            <entry id="shield_maiden_armour_1"><![CDATA[Stara zbroja]]></entry> 
            <entry id="shield_maiden_armour_2"><![CDATA[Płyszczący pancerz]]></entry>
            <entry id="shield_maiden_armour_3"><![CDATA[Honorowa zbroja]]></entry>
            <entry id="shield_maiden_armour_4"><![CDATA["Gwardia konuga"]]></entry>
            <entry id="upgrade_tree_name_shield_maiden.armour"><![CDATA[Zbroja płytowa]]></entry>
 
        <entry id="camping_skill_name_watchful_march"><![CDATA[CZUJNY MARSZ]]></entry>
        <entry id="camping_skill_name_lay_of_hands"><![CDATA[NAKŁADANIE RĄK]]></entry>
        <entry id="camping_skill_name_shield_up"><![CDATA[WYŻEJ TARCZĘ]]></entry>
        <entry id="camping_skill_name_guardian_angel"><![CDATA[ANIOŁ STRÓŻ]]></entry>
 
        <entry id="str_bark_watchful_march"><![CDATA[Bądźcie czujni - zło czai się w ciemności.]]></entry>
        <entry id="str_bark_lay_of_hands"><![CDATA[Chodź tutaj - zaraz złagodzę ten ból.]]></entry>
        <entry id="str_bark_shield_up"><![CDATA[Nic mnie nie złamie!]]></entry>
        <entry id="str_bark_guardian_angel"><![CDATA[Nie martw się - będziesz pod moimi skrzydłami.]]></entry>        
     
 
        <entry id="camping_skill_requirement_bleeding"><![CDATA[Dzięki krwi można spełniać obowiązki - nie może tak się lać.]]></entry>
 
        <entry id="shield_maiden+str_monster_user_selected_targets_kill_pill"><![CDATA[Może i umrę, ale swoje obowiązki...]]></entry>
 
         <entry id="shield_maiden+str_critbyhero"><![CDATA[Zło nie zatriumfuje!]]></entry>
         <entry id="shield_maiden+str_critbyhero"><![CDATA[To nie jest moje ostatnie słowo!]]></entry>
         <entry id="shield_maiden+str_critbyhero"><![CDATA[Strzeżcie się brudasy!]]></entry>
         <entry id="shield_maiden+str_critbyhero"><![CDATA[Trzymać szyk! Walka się nie skończyła!]]></entry>
         <entry id="shield_maiden+str_critbyhero"><![CDATA[Światło przyszło przed świtem!]]></entry>
        
         <entry id="shield_maiden+str_bark_deathsdoor"><![CDATA[Ale... ocaliłam tyle żyć!]]></entry>
       
         <entry id="shield_maiden+str_afflicted_fearful"><![CDATA[*szloch* Frejo, ratuj.....]]></entry>
         
         <entry id="shield_maiden+str_afflicted_paranoia"><![CDATA[Uwaga! Wróg jest wśród nas!]]></entry>
          
         <entry id="shield_maiden+str_afflicted_masochism"><![CDATA[Moim obowiązkiem jest cierpieć za was!]]></entry>
         
         <entry id="shield_maiden+str_afflicted_abusive"><![CDATA[Durnie! Przez waszą głupotę nie mogę was chronić!]]></entry>
         
         <entry id="shield_maiden+str_afflicted_selfishness"><![CDATA[Moje bezpieczeństwo przede wszystkim!]]></entry>
          
         <entry id="shield_maiden+str_afflicted_depression"><![CDATA[Moja służba dobiega końca...]]></entry>
         
         <entry id="shield_maiden+str_afflicted_irrationality"><![CDATA[Krasnoludki na strychu!]]></entry>
        
         <entry id="shield_maiden+str_virtued_stalwart"><![CDATA[Zewrzeć szyk a nic nam się nie stanie!]]></entry>
         
         <entry id="shield_maiden+str_virtued_courageous"><![CDATA[Nikt nie przebije się przez moją tarczę!]]></entry>
         
         <entry id="shield_maiden+str_virtued_focused"><![CDATA[Trzymajcie szyk a zwyciężymy!]]></entry>
         
         <entry id="shield_maiden+str_virtued_powerful"><![CDATA[Wrogowie przebudzili niedźwiedza!]]></entry>
        
         <entry id="shield_maiden+str_virtued_prosperous"><![CDATA[Wszystko idzie tak, jak być powinno!]]></entry>
         
         <entry id="shield_maiden+str_virtued_vigorous"><![CDATA[Służba daje mi siłę!]]></entry>
          
         <entry id="shield_maiden+str_stress_heal_self_stalwart"><![CDATA[To pryszcz!]]></entry>
         <entry id="shield_maiden+str_stress_heal_self_stalwart"><![CDATA[To co robię, jest słuszne!]]></entry>
        
         <entry id="shield_maiden+str_stress_heal_party_courageous"><![CDATA[Trzymajcie się! Mur tarcz jeszcze nie jest przerwany!]]></entry>
         <entry id="shield_maiden+str_stress_heal_party_courageous"><![CDATA[Ich ogień nie stopi naszych serc!]]></entry>
         
         <entry id="shield_maiden+str_buff_random_party_member_focused"><![CDATA[Ej ty! Wyżej garda!]]></entry>
         <entry id="shield_maiden+str_buff_random_party_member_focused"><![CDATA[Uderzaj bez wahania! Jakby co to cię osłonię!]]></entry>
         
         <entry id="shield_maiden+str_buff_party_powerful"><![CDATA[Trzaskać ich po mordach!]]></entry>
         <entry id="shield_maiden+str_buff_party_powerful"><![CDATA[Duchy niedźwiedzi nas wspierają!]]></entry>
          
         <entry id="shield_maiden+str_heal_self_vigorous"><![CDATA[Krew krąży mocniej w mych żyłach!]]></entry>
         <entry id="shield_maiden+str_heal_self_vigorous"><![CDATA[Tym mnie nie zabijecie!]]></entry>
          
         <entry id="shield_maiden+str_bark_stress_fearful"><![CDATA[Tarcza za bardzo mi ciąży...]]></entry>
         <entry id="shield_maiden+str_bark_stress_fearful"><![CDATA[Freja już mnie nie kocha...]]></entry>
         <entry id="shield_maiden+str_bark_stress_paranoid"><![CDATA[Łapy precz zboczeńcu!]]></entry>
         <entry id="shield_maiden+str_bark_stress_paranoid"><![CDATA[To przez niego wpadliśmy!]]></entry>
         <entry id="shield_maiden+str_bark_stress_paranoid"><![CDATA[Mamy wroga wśród nas! Szukajcie zmianom mroku!]]></entry>
         <entry id="shield_maiden+str_bark_stress_masochistic"><![CDATA[Ból odświeża piękne wspomnienia z dzieciństwa...]]></entry>
         <entry id="shield_maiden+str_bark_stress_masochistic"><![CDATA[Połączmy się w bólu!]]></entry>
         <entry id="shield_maiden+str_bark_stress_masochistic"><![CDATA[Moja krew jest... taka piękna...]]></entry>
         <entry id="shield_maiden+str_bark_stress_abusive"><![CDATA[Może i was obronię, ale świat nie będzie z tego zadowolony...]]></entry>
         <entry id="shield_maiden+str_bark_stress_abusive"><![CDATA[Za co zostałam pokarana taką kompaniją?!]]></entry>
         <entry id="shield_maiden+str_bark_stress_abusive"><![CDATA[Już wiem czemu mnie tu konung wysłał - jesteście beznadziejni!]]></entry>
         <entry id="shield_maiden+str_bark_stress_selfish"><![CDATA[Nie powinnam być tu z wami.]]></entry>
         <entry id="shield_maiden+str_bark_stress_selfish"><![CDATA[Powinnam sprzedać was wszystkich i wrócić na północ!]]></entry>
         <entry id="shield_maiden+str_bark_stress_selfish"><![CDATA[Zbyt długo wam pomagałam - teraz wy pomóżcie mi!]]></entry>
         <entry id="shield_maiden+str_bark_stress_depressed"><![CDATA[Wróg jest słoniem a nasze zbroje są tekturą...]]></entry>
         <entry id="shield_maiden+str_bark_stress_depressed"><![CDATA[Moja tarcza i zbroja mają już za dużo skaz...]]></entry>
         <entry id="shield_maiden+str_bark_stress_depressed"><![CDATA[Nie zasługuję na to, by trafić do Valhalli...]]></entry>
         <entry id="shield_maiden+str_bark_stress_irrational"><![CDATA[Kto narobił do niebieskiej szafy!]]></entry>
         <entry id="shield_maiden+str_bark_stress_irrational"><![CDATA[Wszystko gra! Na dachu nie ma żadnych trolli!]]></entry>
         <entry id="shield_maiden+str_bark_stress_irrational"><![CDATA[Tutaj mogłabym postawić domek...]]></entry>
         <entry id="shield_maiden+str_change_pos_back_fearful"><![CDATA[Nie mogę dłużej tu stać!]]></entry>
         <entry id="shield_maiden+str_change_pos_back_fearful"><![CDATA[Wiecie co... lepiej jak się ciutkę przesunę...]]></entry>
         <entry id="shield_maiden+str_change_pos_back_fearful"><![CDATA[Oh Frejo, Frejo...]]></entry>
         <entry id="shield_maiden+str_change_pos_back_paranoid"><![CDATA[Jeżeli nie jesteś zdrajcą to idź na front!]]></entry>
         <entry id="shield_maiden+str_change_pos_back_paranoid"><![CDATA[Nie mogę walczyć na dwóch frontach!]]></entry>
         <entry id="shield_maiden+str_change_pos_back_paranoid"><![CDATA[Muszę mieć baczenie na zdrajców!]]></entry>
         <entry id="shield_maiden+str_change_pos_fwd_masochistic"><![CDATA[By cierpieć na ciebie muszę być bliżej frontu.]]></entry>
         <entry id="shield_maiden+str_change_pos_fwd_masochistic"><![CDATA[Z drogi! Aby służyć muszę cierpieć!]]></entry>
         <entry id="shield_maiden+str_change_pos_fwd_masochistic"><![CDATA[Ooo, wyglądasz na strudzonego? Pozwól, że obowiązek bólu wezmę na siebie.]]></entry>
         <entry id="shield_maiden+str_change_pos_fwd_irrational"><![CDATA[Jak sobie znajdę chłopa, jak nie będę tańczyć?]]></entry>
         <entry id="shield_maiden+str_change_pos_fwd_irrational"><![CDATA[Jestem słoniowym taranem!]]></entry>
         <entry id="shield_maiden+str_change_pos_fwd_irrational"><![CDATA[Atak pupą!]]></entry>
         <entry id="shield_maiden+str_change_pos_back_irrational"><![CDATA[Pupa do przodu - cycki do tyłu!]]></entry>
         <entry id="shield_maiden+str_change_pos_back_irrational"><![CDATA[Jak mam sobie znaleźć chłopa, jak nie będę tańczyć?]]></entry>
         <entry id="shield_maiden+str_change_pos_back_irrational"><![CDATA[Osłaniajcie mnie! Muszę się napić piwa!]]></entry>
         <entry id="shield_maiden+str_change_pos_fwd_depressed"><![CDATA[Zakończcie moje cierpienie!]]></entry>
         <entry id="shield_maiden+str_change_pos_fwd_depressed"><![CDATA[Mi już nic nie pomoże, ale ty możesz się za mną schronić...]]></entry>
         <entry id="shield_maiden+str_change_pos_fwd_depressed"><![CDATA[*we łzach* pozwól mi trafić do Valhalli!]]></entry>
         <entry id="shield_maiden+str_change_pos_back_depressed"><![CDATA[Ty mnie lepiej będziesz osłaniać niż ja ciebie...]]></entry>
         <entry id="shield_maiden+str_change_pos_back_depressed"><![CDATA[Szanse na Valhallę i tak już stracone...]]></entry>
         <entry id="shield_maiden+str_change_pos_back_depressed"><![CDATA[Jestem niczym.....]]></entry>
         <entry id="shield_maiden+str_change_pos_fwd_selfish"><![CDATA[Z drogi szczurze! Zabierasz mi glorię!]]></entry>
         <entry id="shield_maiden+str_change_pos_fwd_selfish"><![CDATA[RAUS! To JA mam zwyciężać!]]></entry>
         <entry id="shield_maiden+str_change_pos_fwd_selfish"><![CDATA[Teraz baba pokaże, jak należy się bić!]]></entry>
         <entry id="shield_maiden+str_change_pos_back_selfish"><![CDATA[Jestem zbyt cenna aby umierać - chroń mnie!]]></entry>
         <entry id="shield_maiden+str_change_pos_back_selfish"><![CDATA[Bądź moją żywą tarczą!]]></entry>
         <entry id="shield_maiden+str_change_pos_back_selfish"><![CDATA[Ja mam was chronić? Dobre żarty!]]></entry>
         <entry id="shield_maiden+str_ignore_command_fearful"><![CDATA[*szepcze* oh Frejo, Frejo...]]></entry>
         <entry id="shield_maiden+str_ignore_command_fearful"><![CDATA[*krzyk* NIE STRASZ MNIE!]]></entry>
         <entry id="shield_maiden+str_ignore_command_fearful"><![CDATA[Co? Mówiłeś coś do mnie?]]></entry>
         <entry id="shield_maiden+str_ignore_command_paranoid"><![CDATA[Wzrok tych kamieni... one coś wiedzą!]]></entry>
         <entry id="shield_maiden+str_ignore_command_paranoid"><![CDATA[Wasze kłamstwa mnie nie naruszą!]]></entry>
         <entry id="shield_maiden+str_ignore_command_paranoid"><![CDATA[Mam się odchylić, byś mnie zmacał, zboczeńcu?]]></entry>
         <entry id="shield_maiden+str_ignore_command_selfish"><![CDATA[Moja zajebistość ich pokona!]]></entry>
         <entry id="shield_maiden+str_ignore_command_selfish"><![CDATA[O, to nagle jestem wam potrzebna? Szkoda, że mam to w nosie!]]></entry>
         <entry id="shield_maiden+str_ignore_command_selfish"><![CDATA[Nie chce mi się...]]></entry>
         <entry id="shield_maiden+str_ignore_command_depressed"><![CDATA[A na cóż to potrzebne?]]></entry>
         <entry id="shield_maiden+str_ignore_command_depressed"><![CDATA[Ja nie chcę!]]></entry>
         <entry id="shield_maiden+str_ignore_command_depressed"><![CDATA[Jestem zbyt gruba, aby być przydatną...]]></entry>
         <entry id="shield_maiden+str_ignore_command_irrational"><![CDATA[Stojąc nieruchomo pomyślą, że jestem posągiem...]]></entry>
         <entry id="shield_maiden+str_ignore_command_irrational"><![CDATA[Trzymać szyk... Trzymać szyk... Trzymać szyk...]]></entry>
         <entry id="shield_maiden+str_ignore_command_irrational"><![CDATA[Nie mogę! Jeszcze jeden ruch a ze zbroi wystrzelą iskry a my wszyscy spłoniemy!]]></entry>
         <entry id="shield_maiden+str_random_command_paranoid"><![CDATA[Nie, nie, nie. Ja już poznałam wasz spisek!]]></entry>
         <entry id="shield_maiden+str_random_command_paranoid"><![CDATA[*śmiech* skłamałam!]]></entry>
         <entry id="shield_maiden+str_random_command_paranoid"><![CDATA[Poznali nasz sekret! Muszę improwizować!]]></entry>
         <entry id="shield_maiden+str_random_command_masochistic"><![CDATA[Nic nie czuję! Co tu robić? Co tu robić? WIEM!]]></entry>
         <entry id="shield_maiden+str_random_command_masochistic"><![CDATA[To sprawi nam przyjemność, nie martw się.]]></entry>
         <entry id="shield_maiden+str_random_command_masochistic"><![CDATA[Aż ręka mnie świeżbi...]]></entry>
         <entry id="shield_maiden+str_random_command_abusive"><![CDATA[Czemóż muszę strzec tych durniów?!]]></entry>
         <entry id="shield_maiden+str_random_command_abusive"><![CDATA[Cholerne bęcwały!]]></entry>
         <entry id="shield_maiden+str_random_command_abusive"><![CDATA[Nie będę słuchać poleceń frajerów!]]></entry>
         <entry id="shield_maiden+str_random_command_selfish"><![CDATA[Kobieca siła!]]></entry>
         <entry id="shield_maiden+str_random_command_selfish"><![CDATA[Przecież wiem co robię...]]></entry>
         <entry id="shield_maiden+str_random_command_selfish"><![CDATA[Och, ach! Wiem co zrobić, by pięknie wyjść!]]></entry>
         <entry id="shield_maiden+str_random_command_depressed"><![CDATA[*we łzach* Wybaczcie mi wszyscy...]]></entry>
         <entry id="shield_maiden+str_random_command_depressed"><![CDATA[Szyk i tak już został przerwany...]]></entry>
         <entry id="shield_maiden+str_random_command_depressed"><![CDATA[Czy ktoś wie co my w ogóle robimy?]]></entry>
         <entry id="shield_maiden+str_random_command_irrational"><![CDATA[*zwierzęcy krzyk*]]></entry>
         <entry id="shield_maiden+str_random_command_irrational"><![CDATA[Uważaj! Mucha!]]></entry>
         <entry id="shield_maiden+str_random_command_irrational"><![CDATA[Na drakkary i do przodu!]]></entry>
         <entry id="shield_maiden+str_random_command_irrational"><![CDATA[Tańcząca z trollami!]]></entry>
         <entry id="shield_maiden+str_bark_stress_camp_fearful"><![CDATA[Moja tarcza jest zbyt słaba...]]></entry>
         <entry id="shield_maiden+str_bark_stress_camp_fearful"><![CDATA[Przeciw tych abominacjom stal jest zbyt słaba...]]></entry>
         <entry id="shield_maiden+str_bark_stress_camp_fearful"><![CDATA[Konung Ruryk nie doprowadziłby nas w tę pułapkę...]]></entry>
         <entry id="shield_maiden+str_bark_stress_camp_paranoid"><![CDATA[Coś mi się wydaje, że zamieniasz się w świnioludzia. Mam na Ciebie oko!]]></entry>
         <entry id="shield_maiden+str_bark_stress_camp_paranoid"><![CDATA[Każdy, kto będzie chciał złamać mnie za tyłek, zostanie nabity na pal!]]></entry>
         <entry id="shield_maiden+str_bark_stress_camp_paranoid"><![CDATA[Kto nie pije ten donosi!]]></entry>
         <entry id="shield_maiden+str_bark_stress_camp_paranoid"><![CDATA[Wśród nas jest zdrajca. Przyznajcie się bez bicia!]]></entry>
         <entry id="shield_maiden+str_bark_stress_camp_masochistic"><![CDATA[Nie potrzebuję poduszki - twarda i zimna tarcza podadzą mi ból.]]></entry>
         <entry id="shield_maiden+str_bark_stress_camp_masochistic"><![CDATA[Zimno hartuje a ciepło rozmiękcza. Zgaście ogień!]]></entry>
         <entry id="shield_maiden+str_bark_stress_camp_masochistic"><![CDATA[*nacina delikatnie skórę* jeszcze po kropelce...]]></entry>
         <entry id="shield_maiden+str_bark_stress_camp_abusive"><![CDATA[Mam nadzieję, że nie będziecie chrapać - nie chciałabym przez was zginąć.]]></entry>
         <entry id="shield_maiden+str_bark_stress_camp_abusive"><![CDATA[Nie wstyd wam, że baba musi was chronić?]]></entry>
         <entry id="shield_maiden+str_bark_stress_camp_abusive"><![CDATA[Zamiast spać powinniście ćwiczyć, niedojdy.]]></entry>
         <entry id="shield_maiden+str_bark_stress_camp_selfish"><![CDATA[Ma ktoś grzebyczek? Muszę się uczesać...]]></entry>
         <entry id="shield_maiden+str_bark_stress_camp_selfish"><![CDATA[To jest pewne - Freja mnie kocha bardziej niż was.]]></entry>
         <entry id="shield_maiden+str_bark_stress_camp_selfish"><![CDATA[Czy ten chleb jest bezglutenowy? Fuj!]]></entry>
         <entry id="shield_maiden+str_bark_stress_camp_depressed"><![CDATA[*szept* utraciliśmy wszelkie łaski...]]></entry>
         <entry id="shield_maiden+str_bark_stress_camp_depressed"><![CDATA[Nawet jak spalimy cały chlew - świnioludzie i tak nas zwycięża...]]></entry>
         <entry id="shield_maiden+str_bark_stress_camp_depressed"><![CDATA[Moja tarcza jest zbyt słaba... Nie ochronię was...]]></entry>
         <entry id="shield_maiden+str_bark_stress_camp_irrational"><![CDATA[To wszystko wina mężczyzn! Samiec twój wróg!]]></entry>
         <entry id="shield_maiden+str_bark_stress_camp_irrational"><![CDATA[Nie martwię się o uderzenia w głowę - mózg mam w mym pięknym tyłku.]]></entry>
         <entry id="shield_maiden+str_bark_stress_camp_irrational"><![CDATA[To leże powinno należeć dla niedźwiedzi.]]></entry>
         <entry id="shield_maiden+str_mark_self_masochistic"><![CDATA[Patrz, jak się dla ciebie odsłaniam!]]></entry>
         <entry id="shield_maiden+str_mark_self_masochistic"><![CDATA[*uwodzicielsko* Ojejku, jejku! Moja tarcza jest taaka słaba po lewej stronie!]]></entry>
         <entry id="shield_maiden+str_mark_self_depressed"><![CDATA[Zakończcie to...]]></entry>
         <entry id="shield_maiden+str_mark_self_depressed"><![CDATA[Stracone marzenia...]]></entry>
         <entry id="shield_maiden+str_mark_self_irrational"><![CDATA[Ej! Kto mnie klepną w tyłek?]]></entry>
         <entry id="shield_maiden+str_mark_self_irrational"><![CDATA[To są przyjaciele! Napijmy się z nimi!]]></entry>
         <entry id="shield_maiden+str_attack_friendly_paranoid"><![CDATA[Kłamca!]]></entry>
         <entry id="shield_maiden+str_attack_friendly_paranoid"><![CDATA[Nie uszykasz mnie!]]></entry>
         <entry id="shield_maiden+str_attack_friendly_abusive"><![CDATA[Pozbędę się tego ciężaru!]]></entry>
         <entry id="shield_maiden+str_attack_friendly_abusive"><![CDATA[Twoja obecność jest obrazą dla Frei!]]></entry>
         <entry id="shield_maiden+str_attack_friendly_irrational"><![CDATA[On ma krew trolli!]]></entry>
         <entry id="shield_maiden+str_attack_friendly_irrational"><![CDATA[Masz cienie pod oczami! Zabiję je!]]></entry>
         <entry id="shield_maiden+str_attack_self_masochistic"><![CDATA[Nic nie czuję... czy ja jeszcze żyję? Sprawdzę to!]]></entry>
         <entry id="shield_maiden+str_attack_self_masochistic"><![CDATA[W życiu mam za mało radości. Przynajmniej ta rana da mi pocieszenie.]]></entry>
         <entry id="shield_maiden+str_attack_self_depressed"><![CDATA[Mam już dosyć tego wszystkiego...]]></entry>
         <entry id="shield_maiden+str_attack_self_depressed"><![CDATA[Ciemność już mnie pożarła...]]></entry>
         <entry id="shield_maiden+str_attack_self_irrational"><![CDATA[Czy aby na pewno ta ręk jest moja?]]></entry>
         <entry id="shield_maiden+str_attack_self_irrational"><![CDATA[Drawle rąbią w mojej głowie! Trzeba ich uwolnić!]]></entry>
         <entry id="shield_maiden+str_block_combat_retreat_paranoid"><![CDATA[Jak uciekniemy to strzelą nam w plecy!]]></entry>
         <entry id="shield_maiden+str_block_combat_retreat_paranoid"><![CDATA[To byłaby zdrada!]]></entry>
         <entry id="shield_maiden+str_block_combat_retreat_depressed"><![CDATA[Za ścianą czeka nam tylko śmierć...]]></entry>
         <entry id="shield_maiden+str_block_combat_retreat_depressed"><![CDATA[Nie - nie zdołam nikogo obronić jak będziemy się cofać.]]></entry>
         <entry id="shield_maiden+str_block_combat_retreat_masochistic"><![CDATA[Skorupa ze strupów najlepszą obroną!]]></entry>
         <entry id="shield_maiden+str_block_combat_retreat_masochistic"><![CDATA[Mamy za mało blizn!]]></entry>
         <entry id="shield_maiden+str_block_combat_retreat_irrational"><![CDATA[Nie musimy uciekać - moja tarcza osłoni nas wszystkich!]]></entry>
         <entry id="shield_maiden+str_block_combat_retreat_irrational"><![CDATA[A potem będą mówić, że baba się nie nadaje do walki? Tego chcecie!]]></entry>
         <entry id="shield_maiden+str_comment_self_hit_fearful"><![CDATA[Nie uda mi się zrealizować obietnicy...]]></entry>
         <entry id="shield_maiden+str_comment_self_hit_fearful"><![CDATA[Jak długo zdołam jeszcze się bronić?]]></entry>
         <entry id="shield_maiden+str_comment_self_hit_paranoid"><![CDATA[Kto wydał lukę mojej obrony?!]]></entry>
         <entry id="shield_maiden+str_comment_self_hit_paranoid"><![CDATA[To nie było możliwe bez donosów!]]></entry>
         <entry id="shield_maiden+str_comment_self_hit_selfish"><![CDATA[Spokojnie panowie - tak być miało *szeptem* a może nie...]]></entry>
         <entry id="shield_maiden+str_comment_self_hit_selfish"><![CDATA[Jak moj wspaniałość mogła tak zawieść?]]></entry>
         <entry id="shield_maiden+str_comment_self_hit_masochistic"><![CDATA[Widzieliście? Specjalnie odsunęłam tarczę!]]></entry>
         <entry id="shield_maiden+str_comment_self_hit_masochistic"><![CDATA[Cóż za piękny odcień czerwieni...]]></entry>
         <entry id="shield_maiden+str_comment_self_hit_irrational"><![CDATA[*szpieszki*]]></entry>
         <entry id="shield_maiden+str_comment_self_hit_irrational"><![CDATA[Niedźwiedzia furia zaczyna rosnąć!]]></entry>
         <entry id="shield_maiden+str_comment_self_missed_fearful"><![CDATA[*szybki oddech* Nie mogłam...]]></entry>
         <entry id="shield_maiden+str_comment_self_missed_fearful"><![CDATA[Te ich twarze! One są zbyt przerażające!]]></entry>
         <entry id="shield_maiden+str_comment_self_missed_paranoid"><![CDATA[Bo muszę się osłaniać przed wami!]]></entry>
         <entry id="shield_maiden+str_comment_self_missed_paranoid"><![CDATA[Kto im przyklasną?]]></entry>
         <entry id="shield_maiden+str_comment_self_missed_masochistic"><![CDATA[Zabawa będzie trwać dłużej!]]></entry>
         <entry id="shield_maiden+str_comment_self_missed_masochistic"><![CDATA[Może nie trafiłam, ale patrz jak ładnie obtarłam się o tarczę!]]></entry>
         <entry id="shield_maiden+str_comment_self_missed_irrational"><![CDATA[Nie trafiłam, bo w ostatniej zauważyłam torbiel pełną toksyn. To by nas zabiło. Dziękujcie!]]></entry>
         <entry id="shield_maiden+str_comment_self_missed_irrational"><![CDATA[Za dużo potu...]]></entry>
         <entry id="shield_maiden+str_comment_ally_attack_hit_selfish"><![CDATA[Mogłabym to zrobić lepiej!]]></entry>
         <entry id="shield_maiden+str_comment_ally_attack_hit_selfish"><![CDATA[I cała gloria dla ciebie...]]></entry>
         <entry id="shield_maiden+str_comment_ally_attack_hit_abusive"><![CDATA[Jak takiej paskudzie się udało trafić?!]]></entry>
         <entry id="shield_maiden+str_comment_ally_attack_hit_abusive"><![CDATA[Ten cios był taaaki paskudny...]]></entry>
         <entry id="shield_maiden+str_comment_ally_attack_hit_irrational"><![CDATA[Zielone mrówki wszystko to przepowiedziały!]]></entry>
         <entry id="shield_maiden+str_comment_ally_attack_hit_irrational"><![CDATA[Dobre. Zasłużyłeś na krakersa!]]></entry>
         <entry id="shield_maiden+str_comment_ally_attack_missed_fearful"><![CDATA[Ale, ale jak to?!]]></entry>
         <entry id="shield_maiden+str_comment_ally_attack_missed_fearful"><![CDATA[Przez ciebie zginiemy!]]></entry>
         <entry id="shield_maiden+str_comment_ally_missed_paranoid"><![CDATA[To pudło nie mogło być przypadkiem!]]></entry>
         <entry id="shield_maiden+str_comment_ally_missed_paranoid"><![CDATA[Składałeś przysięgę tym potworom?]]></entry>
         <entry id="shield_maiden+str_comment_ally_attack_missed_abusive"><![CDATA[I ja muszę bronić taką niezdarę?]]></entry>
         <entry id="shield_maiden+str_comment_ally_attack_missed_abusive"><![CDATA[Lepiej byś się nadawał na żywą tarczę!]]></entry>
         <entry id="shield_maiden+str_comment_ally_attack_missed_selfish"><![CDATA[Mam nadzieję, że moja uroda cię nie rozproszyła.]]></entry>
         <entry id="shield_maiden+str_comment_ally_attack_missed_selfish"><![CDATA[Gdybym JA to robiło, to byłoby idealnie!]]></entry>
         <entry id="shield_maiden+str_comment_ally_attack_missed_irrational"><![CDATA[Dobra robota!]]></entry>
         <entry id="shield_maiden+str_comment_ally_attack_missed_irrational"><![CDATA[Dzięki tobie będę mogła spełnić swoją obietnicę.]]></entry>
         <entry id="shield_maiden+str_comment_ally_hit_fearful"><![CDATA[Cóż to za flaki!]]></entry>
         <entry id="shield_maiden+str_comment_ally_hit_fearful"><![CDATA[Ich zawziętość wzrasta!]]></entry>
         <entry id="shield_maiden+str_comment_ally_hit_paranoid"><![CDATA[Ładnie się maskujesz...]]></entry>
         <entry id="shield_maiden+str_comment_ally_hit_paranoid"><![CDATA[Fajny cios... ale nie musiałeś przy okazji łapać mnie za tyłek!]]></entry>
         <entry id="shield_maiden+str_comment_ally_hit_masochistic"><![CDATA[*płacz* to we mnie winieneś uderzyć!]]></entry>
         <entry id="shield_maiden+str_comment_ally_hit_masochistic"><![CDATA[Jakaś piękna krew!]]></entry>
         <entry id="shield_maiden+str_comment_ally_hit_abusive"><![CDATA[Za tak paskudny cios mój nauczyciel kazałby tobie stać cały dzień w morzu!]]></entry>
         <entry id="shield_maiden+str_comment_ally_hit_abusive"><![CDATA[Nie tak! Z lewej na prawą - po prawej lepiej się chronią! Kto cię uczył?!]]></entry>
         <entry id="shield_maiden+str_comment_ally_hit_irrational"><![CDATA[*śmieszki*]]></entry>
         <entry id="shield_maiden+str_comment_ally_hit_irrational"><![CDATA[Widzę, że masz oko koboldów.]]></entry>
         <entry id="shield_maiden+str_comment_ally_missed_fearful"><![CDATA[Chroń nas Frejo!]]></entry>
         <entry id="shield_maiden+str_comment_ally_missed_fearful"><![CDATA[Nie... nie... nie...]]></entry>
         <entry id="shield_maiden+str_comment_ally_missed_irrational"><![CDATA[Spróbuj może lewą stopą.]]></entry>
         <entry id="shield_maiden+str_comment_ally_missed_irrational"><![CDATA[To przez nieporęczną broń. Spróbuj patyka z kupą!]]></entry>
         <entry id="shield_maiden+str_block_move_fearful"><![CDATA[O nie! Tu jestem bezpieczna!]]></entry>
         <entry id="shield_maiden+str_block_move_fearful"><![CDATA[Jak się przesunę to mnie zabiją!]]></entry>
         <entry id="shield_maiden+str_block_move_paranoid"><![CDATA[Ta, jasne. Chcesz mnie zmacać na boku, co? Nie dam się!]]></entry>
         <entry id="shield_maiden+str_block_move_paranoid"><![CDATA[Nie zaufam tobie!]]></entry>
         <entry id="shield_maiden+str_block_move_masochistic"><![CDATA[A po co? Tu mogę doświadczyć uroku bitwy!]]></entry>
         <entry id="shield_maiden+str_block_move_masochistic"><![CDATA[Mogłabym, ale tu jest mi tak dobrze...]]></entry>
         <entry id="shield_maiden+str_block_move_abusive"><![CDATA[Nie zmienię pozycji z tą... paskudą!]]></entry>
         <entry id="shield_maiden+str_block_move_abusive"><![CDATA[By chronić tego dziada muszę stać TU!]]></entry>
         <entry id="shield_maiden+str_block_move_irrational"><![CDATA[To on narobił w niebieskiej szafie - niechaj tam stoi dalej za karę!]]></entry>
         <entry id="shield_maiden+str_block_move_irrational"><![CDATA[Kamyk rzucony w ogień się nie spali...]]></entry>
         <entry id="shield_maiden+str_block_item_paranoid"><![CDATA[W tym czuję truciznę!]]></entry>
         <entry id="shield_maiden+str_block_item_paranoid"><![CDATA[A tuż po tym wbijesz mi nóż w plecy?]]></entry>
         <entry id="shield_maiden+str_block_item_masochistic"><![CDATA[Ja tego nie potrzebuję!]]></entry>
         <entry id="shield_maiden+str_block_item_masochistic"><![CDATA[Mi wystarczy tylko moja tarcza!]]></entry>
         <entry id="shield_maiden+str_block_item_depressed"><![CDATA[Ja mam bronić a nie samą być bronioną.]]></entry>
         <entry id="shield_maiden+str_block_item_depressed"><![CDATA[Moja przysięga wyklucza użycie tego w tej sytuacji.]]></entry>
         <entry id="shield_maiden+str_block_item_irrational"><![CDATA[To zostało zrobione przez trolle - nie użyję tego.]]></entry>
         <entry id="shield_maiden+str_block_item_irrational"><![CDATA[Zielone mrówki odradzaja użycie tego...]]></entry>
         <entry id="shield_maiden+str_block_heal_paranoid"><![CDATA[Twoje leczenie może mnie tylko osłabić.]]></entry>
         <entry id="shield_maiden+str_block_heal_paranoid"><![CDATA[Ta moc skieruje ich wzrok na mnie!]]></entry>
         <entry id="shield_maiden+str_block_heal_paranoid"><![CDATA[Strawione kości mi pomogą bardziej niż TY!]]></entry>
         <entry id="shield_maiden+str_block_heal_masochistic"><![CDATA[Cierpienie jest dla mnie - łaska dla was.]]></entry>
         <entry id="shield_maiden+str_block_heal_masochistic"><![CDATA[Aby was bronić muszę czuć bół!]]></entry>
         <entry id="shield_maiden+str_block_heal_masochistic"><![CDATA[Bez bólu będę zbyt słaba by spełnić swoje obietnice!]]></entry>
         <entry id="shield_maiden+str_block_heal_depressed"><![CDATA[I tak już złamałam obietnicę - nie marnuj na mnie czasu...]]></entry>
         <entry id="shield_maiden+str_block_heal_depressed"><![CDATA[Moja misja stracona, nic mi nie pomoże.]]></entry>
         <entry id="shield_maiden+str_block_heal_depressed"><![CDATA[*niemy szloch*]]></entry>
         <entry id="shield_maiden+str_block_heal_irrational"><![CDATA[Chcesz by mi tarcza przerdzewiała?!]]></entry>
         <entry id="shield_maiden+str_block_heal_irrational"><![CDATA[Mój miecz złapał bita. Słuchajcie!]]></entry>
         <entry id="shield_maiden+str_block_heal_irrational"><![CDATA[Nie widzę gwiazdy północnej... Ciekawe czemu...]]></entry>
         <entry id="shield_maiden+str_block_buff_paranoid"><![CDATA[Nie przyjmuję wsparcia od krzywoprzysięzców!]]></entry>
         <entry id="shield_maiden+str_block_buff_paranoid"><![CDATA[Chcesz abym złamała swój kodeks honorowy?!]]></entry>
         <entry id="shield_maiden+str_block_buff_paranoid"><![CDATA[To ma na celu osłabić moją wolę!]]></entry>
         <entry id="shield_maiden+str_block_buff_masochist"><![CDATA[Daj wsparcie tyłom!]]></entry>
         <entry id="shield_maiden+str_block_buff_masochist"><![CDATA[JA jestem wsparciem i tarczą dla was!]]></entry>
         <entry id="shield_maiden+str_block_buff_masochist"><![CDATA[Precz stąd! Zabierasz mi szansę na Valhallę!]]></entry>
         <entry id="shield_maiden+str_block_buff_depressed"><![CDATA[Nie naprawisz ani mej duszy ani mej tarczy...]]></entry>
         <entry id="shield_maiden+str_block_buff_depressed"><![CDATA[*beznamiętnie patrzy na ciebie*]]></entry>
         <entry id="shield_maiden+str_block_buff_depressed"><![CDATA[Jak to przyjmę to nie dojdę do Valhalli...]]></entry>
         <entry id="shield_maiden+str_block_buff_irrational"><![CDATA[Wężowe nasienie we mnie nie wejdzie!]]></entry>
         <entry id="shield_maiden+str_block_buff_irrational"><![CDATA[Straaaszne rzeczy się stają, kiedy stal zastąpić świniną...]]></entry>
         <entry id="shield_maiden+str_block_buff_irrational"><![CDATA[Biały szkwał mnie nie dosięgnie!]]></entry>
         <entry id="shield_maiden+str_monster_attack_unholy_smite"><![CDATA[Chcą nam roztrzaskać dusze!]]></entry>
         <entry id="shield_maiden+str_monster_attack_unholy_judgement"><![CDATA[Potrzebuję wsparcia od was! TERAZ!]]></entry>
         <entry id="shield_maiden+str_monster_attack_unholy_curse"><![CDATA[Martwi robią drwa w mojej głowie!]]></entry>
         <entry id="shield_maiden+str_bark_encourage"><![CDATA[Kiedy przyjedziemy do mego domu, to posmakujesz wspaniałego miodu!]]></entry>
         <entry id="shield_maiden+str_bark_encourage"><![CDATA[Na wypirawie konunga Ruryka trafiliśmy do mroczniejszego lasu - tutaj masz łatwiej.]]></entry>
         <entry id="shield_maiden+str_bark_first_aid"><![CDATA[Trochę mazi oraz popiołu i będzie dobrze...]]></entry>
         <entry id="shield_maiden+str_bark_first_aid"><![CDATA[Na razie pomogło. Postaraj się by nie było potrzeby raz jeszcze...]]></entry>
         <entry id="shield_maiden+str_bark_pep_talk"><![CDATA[U konunga Haralda bawiliśmy się w taki sposób...]]></entry>
         <entry id="shield_maiden+str_bark_pep_talk"><![CDATA[Nawet jak zginiemy to Valhalla będzie dla nas otwarta!]]></entry>
         <entry id="shield_maiden+str_bark_hobby"><![CDATA[*czyści tarczę*.]]></entry>
         <entry id="shield_maiden+str_bark_hobby"><![CDATA[Cała drużyna konunga Ruryka mogłaby się tutaj zmieścić!]]></entry>
         <entry id="shield_maiden+str_bark_hobby"><![CDATA[*modli się* O ukochana Frejo...]]></entry>
         <entry id="shield_maiden+str_campingSkillUseBalk_fearful"><![CDATA[Może mrok nas nie pożre...]]></entry>
         <entry id="shield_maiden+str_campingSkillUseBalk_fearful"><![CDATA[Może tarcza osłoni mnie przed ciemnością?]]></entry>
         <entry id="shield_maiden+str_campingSkillUseBalk_paranoid"><![CDATA[Żaden z was mnie nie zmolestuje! Śpię czujnie!]]></entry>
         <entry id="shield_maiden+str_campingSkillUseBalk_paranoid"><![CDATA[Kamienie szepczą o zdradzie...]]></entry>
         <entry id="shield_maiden+str_campingSkillUseBalk_masochistic"><![CDATA[Za zimno... włoże stopy do ogniska...]]></entry>
         <entry id="shield_maiden+str_campingSkillUseBalk_masochistic"><![CDATA[Dzisiaj odbędę się bez jedzenia.]]></entry>
         <entry id="shield_maiden+str_campingSkillUseBalk_masochistic"><![CDATA[Włożę sobie kamyki pod zbroję, bo jest zbyt wygodna...]]></entry>
         <entry id="shield_maiden+str_campingSkillUseBalk_abusive"><![CDATA[Kto się spierdział!]]></entry>
         <entry id="shield_maiden+str_campingSkillUseBalk_abusive"><![CDATA[Wasz smród przeszkadzałby nawet trollom...]]></entry>
         <entry id="shield_maiden+str_campingSkillUseBalk_abusive"><![CDATA[Powinnam was porzucić dawno temu...]]></entry>
         <entry id="shield_maiden+str_campingSkillUseBalk_selfish"><![CDATA[Jestem piękna i urocza. Tutaj się tylko marnuję...]]></entry>
         <entry id="shield_maiden+str_campingSkillUseBalk_selfish"><![CDATA[Najukochańsza córa Frei - to ja!]]></entry>
         <entry id="shield_maiden+str_campingSkillUseBalk_selfish"><![CDATA[Tylko dzięki mojej tarczy i sztuce jeszcze żyjemy.]]></entry>
         <entry id="shield_maiden+str_campingSkillUseBalk_depressed"><![CDATA[Gorzej niż w szałasie z trawy...]]></entry>
         <entry id="shield_maiden+str_campingSkillUseBalk_depressed"><![CDATA[Wrócimy na tarczy albo w ogóle...]]></entry>
         <entry id="shield_maiden+str_campingSkillUseBalk_depressed"><![CDATA[U ludów dzikszych niż moi krewni na płotach nabija się głowy swoich wrogów.]]></entry>
         <entry id="shield_maiden+str_campingSkillUseBalk_irrational"><![CDATA[Czy moja tarcza będzie mogła kiedyś latać?]]></entry>
         <entry id="shield_maiden+str_campingSkillUseBalk_irrational"><![CDATA[Jak schowam głowę pod tarczą to jestem niewidzialna!]]></entry>
         <entry id="shield_maiden+str_campingSkillUseBalk_irrational"><![CDATA[Czuję zapach smażonych biedronek...]]></entry>
         <entry id="shield_maiden+str_campingSkillBenefitBalk_fearful"><![CDATA[Może mrok nas nie pożre...]]></entry>
         <entry id="shield_maiden+str_campingSkillBenefitBalk_fearful"><![CDATA[Może tarcza osłoni mnie przed ciemnością?]]></entry>
         <entry id="shield_maiden+str_campingSkillBenefitBalk_paranoid"><![CDATA[Żaden z was mnie nie zmolestuje! Śpię czujnie!]]></entry>
         <entry id="shield_maiden+str_campingSkillBenefitBalk_paranoid"><![CDATA[Kamienie szepczą o zdradzie...]]></entry>
         <entry id="shield_maiden+str_campingSkillBenefitBalk_masochist"><![CDATA[Za zimno... włoże stopy do ogniska...]]></entry>
         <entry id="shield_maiden+str_campingSkillBenefitBalk_masochist"><![CDATA[Włożę sobie kamyki pod zbroję, bo jest zbyt wygodna...]]></entry>
         <entry id="shield_maiden+str_campingSkillBenefitBalk_abusive"><![CDATA[Słaba nuta...]]></entry>
         <entry id="shield_maiden+str_campingSkillBenefitBalk_abusive"><![CDATA[[Kto się spierdział!]]></entry>
         <entry id="shield_maiden+str_campingSkillBenefitBalk_selfish"><![CDATA[Tylko dzięki mojej tarczy i sztuce jeszcze żyjemy.]]></entry>
         <entry id="shield_maiden+str_campingSkillBenefitBalk_selfish"><![CDATA[*Jestem piękna i urocza. Tutaj się tylko marnuję...]]></entry>
         <entry id="shield_maiden+str_campingSkillBenefitBalk_depressed"><![CDATA[Gorzej niż w szałasie z trawy...]]></entry>
         <entry id="shield_maiden+str_campingSkillBenefitBalk_depressed"><![CDATA[Wrócimy na tarczy albo w ogóle...]]></entry>
         <entry id="shield_maiden+str_campingSkillBenefitBalk_irrational"><![CDATA[Jak schowam głowę pod tarczą to jestem niewidzialna!]]></entry>
         <entry id="shield_maiden+str_campingSkillBenefitBalk_irrational"><![CDATA[Czuję zapach smażonych biedronek...]]></entry>
         <entry id="shield_maiden+str_campingMealBalk_paranoid"><![CDATA[Ta strawa została przeklęta przez Freję.]]></entry>
         <entry id="shield_maiden+str_campingMealBalk_paranoid"><![CDATA[To jest padlina a nie jedzenei!]]></entry>
         <entry id="shield_maiden+str_campingMealBalk_masochist"><![CDATA[Muszę się odchudzać.]]></entry>
         <entry id="shield_maiden+str_campingMealBalk_masochist"><![CDATA[Dzięki, najadłam się już kamieni.]]></entry>
         <entry id="shield_maiden+str_campingMealBalk_masochist"><![CDATA[Siłą woli mogę zablokować głód.]]></entry>
         <entry id="shield_maiden+str_campingMealBalk_depressed"><![CDATA[Daj to komuś, kto naprawdę potrzebuje.]]></entry>
         <entry id="shield_maiden+str_campingMealBalk_depressed"><![CDATA[Nie mogę was bronić, jeżeli nie będziecie najedzeni.]]></entry>
         <entry id="shield_maiden+str_campingMealBalk_depressed"><![CDATA[To mnie niepotrzebnie pogrubi...]]></entry>
         <entry id="shield_maiden+str_campingMealBalk_irrational"><![CDATA[To mięso ma w sobie robaki!]]></entry>
         <entry id="shield_maiden+str_campingMealBalk_irrational"><![CDATA[Chciałabym posmakować kiszonych ryb...]]></entry>   
    </language>
 
 
 
 
 
</root>