{
    "party_names":
    [
  {
    "id": "3081",
    "required_hero_class": [
      "leper",
      "crusader",
      "librarian",
      "occultis"
    ]
  },
  {
    "id": "3082",
    "required_hero_class": [
      "vestal",
      "vestal",
      "librarian",
      "librarian"
    ]
  },
  {
    "id": "3083",
    "required_hero_class": [
      "crusader",
      "houndmaster",
      "grave_robber",
      "librarian"
    ]
  },
  {
    "id": "3084",
    "required_hero_class": [
      "thrall",
      "leper",
      "librarian",
      "lamia"
    ]
  },
  {
    "id": "3085",
    "required_hero_class": [
      "thrall",
      "leper",
      "highwayman",
      "librarian"
    ]
  },
  {
    "id": "3086",
    "required_hero_class": [
      "leper",
      "man_at_arms",
      "crusader",
      "librarian"
    ]
  },
  {
    "id": "3087",
    "required_hero_class": [
      "hood",
      "plague_doctor",
      "antiquarian",
      "librarian"
    ]
  },
  {
    "id": "3088",
    "required_hero_class": [
      "twilight_knight",
      "occultis",
      "antiquarian",
      "librarian"
    ]
  },
  {
    "id": "3089",
    "required_hero_class": [
      "hellion",
      "hood",
      "grave_robber",
      "librarian"
    ]
  },
  {
    "id": "3090",
    "required_hero_class": [
      "man_at_arms",
      "highwayman",
      "arbalest",
      "librarian"
    ]
  },
  {
    "id": "3091",
    "required_hero_class": [
      "librarian",
      "librarian",
      "librarian",
      "librarian"
    ]
  },
  {
    "id": "3092",
    "required_hero_class": [
      "abomination",
      "highwayman",
      "librarian",
      "occultis"
    ]
  },
  {
    "id": "3093",
    "required_hero_class": [
      "abomination",
      "vestal",
      "librarian",
      "occultis"
    ]
  },
  {
    "id": "3094",
    "required_hero_class": [
      "occultis",
      "librarian",
      "plague_doctor",
      "antiquarian"
    ]
  },
  {
    "id": "3095",
    "required_hero_class": [
      "flagellant",
      "crusader",
      "vestal",
      "librarian"
    ]
  },
  {
    "id": "3096",
    "required_hero_class": [
      "leper",
      "plague_doctor",
      "librarian",
      "arbalest"
    ]
  },
  {
    "id": "3097",
    "required_hero_class": [
      "leper",
      "librarian",
      "librarian",
      "librarian"
    ]
  },
  {
    "id": "3098",
    "required_hero_class": [
      "hellion",
      "man_at_arms",
      "crusader",
      "librarian"
    ]
  },
  {
    "id": "3099",
    "required_hero_class": [
      "",
      "librarian",
      "librarian",
      "librarian"
    ]
  },
  {
    "id": "3100",
    "required_hero_class": [
      "lamia",
      "lamia",
      "lamia",
      "librarian"
    ]
  },
  {
    "id": "3101",
    "required_hero_class": [
      "occultis",
      "vestal",
      "librarian",
      "arbalest"
    ]
  },
  {
    "id": "3102",
    "required_hero_class": [
      "antiquarian",
      "abomination",
      "occultis",
      "librarian"
    ]
  },
  {
    "id": "3103",
    "required_hero_class": [
      "phantom",
      "antiquarian",
      "hood",
      "librarian"
    ]
  },
  {
    "id": "3104",
    "required_hero_class": [
      "bounty_hunter",
      "occultis",
      "plague_doctor",
      "librarian"
    ]
  },
  {
    "id": "3105",
    "required_hero_class": [
      "seraph",
      "abomination",
      "hollow",
      "librarian"
    ]
  },
  {
    "id": "3106",
    "required_hero_class": [
      "flagellant",
      "hood",
      "lamia",
      "librarian"
    ]
  },
  {
    "id": "3107",
    "required_hero_class": [
      "thrall",
      "highwayman",
      "bounty_hunter",
      "librarian"
    ]
  },
  {
    "id": "3108",
    "required_hero_class": [
      "leper",
      "crusader",
      "vestal",
      "librarian"
    ]
  },
  {
    "id": "3109",
    "required_hero_class": [
      "shieldbreaker",
      "abomination",
      "hood",
      "librarian"
    ]
  },
  {
    "id": "3110",
    "required_hero_class": [
      "highwayman",
      "grave_robber",
      "phantom",
      "librarian"
    ]
  },
  {
    "id": "3111",
    "required_hero_class": [
      "seraph",
      "phantom",
      "tusk",
      "librarian"
    ]
  }
  
    ]

}